Workbook

Sheet Price Groups
A1: Price Groups & Assumptions
A3: Cost multiplier – exchange rate | B3: 15
A4: Cost multiplier – landed-cost factor | B4: 1.5
A5: Total cost multiplier (Shopify cost × this = EGP cost) | B5: =B3*B4 -> 22.5
A7: SAR→EGP rate used in current prices | B7: 12.5
A8: SAR→EGP rate today (22 Oct 2026) | B8: 14.74
A9: Currency increase (target average price increase) | B9: =B8/B7-1 -> 0.1792
A10: AlBaik meal cost at old rate (EGP) | B10: 370
A11: AlBaik meal NEW price (EGP) – all AlBaik items get the same % | B11: 669 | C11: =B11/580-1 -> 0.15344828 | D11: ← increase applied to every AlBaik item
A12: Group | B12: Name | C12: Increase % | D12: Assignment rule | E12: # Items | F12: Revenue (EGP, 2026) | G12: Revenue share | H12: Contribution
A13: 1 | B13: Group 1 | C13: 0.22 | D13: Margin < 25%, or slow movers (bottom 20% of revenue), or unsold items. AlBaik (cost rises with the riyal). | E13: =COUNTIFS('New Prices'!$R:$R,A13,'New Prices'!$C:$C,"<>Variant") -> 954 | F13: =SUMIFS('New Prices'!$K:$K,'New Prices'!$R:$R,A13,'New Prices'!$K:$K,">0") -> 4074378.4 | G13: =IF($F$18=0,0,F13/$F$18) -> 0.37380653 | H13: =G13*C13 -> 0.082237436
A14: 2 | B14: Group 2 | C14: 0.18 | D14: Core sellers (top 80% of revenue) with 25–40% margin, or no cost in Shopify | E14: =COUNTIFS('New Prices'!$R:$R,A14,'New Prices'!$C:$C,"<>Variant") -> 62 | F14: =SUMIFS('New Prices'!$K:$K,'New Prices'!$R:$R,A14,'New Prices'!$K:$K,">0") -> 1555790.6 | G14: =IF($F$18=0,0,F14/$F$18) -> 0.14273703 | H14: =G14*C14 -> 0.025692665
A15: 3 | B15: Group 3 | C15: 0.16 | D15: Core sellers (45–80% cumulative revenue) with margin ≥ 40% | E15: =COUNTIFS('New Prices'!$R:$R,A15,'New Prices'!$C:$C,"<>Variant") -> 153 | F15: =SUMIFS('New Prices'!$K:$K,'New Prices'!$R:$R,A15,'New Prices'!$K:$K,">0") -> 2655599.6 | G15: =IF($F$18=0,0,F15/$F$18) -> 0.24363974 | H15: =G15*C15 -> 0.038982358
A16: 4 | B16: Group 4 | C16: 0.15 | D16: Top revenue items (first 45% of revenue) with margin ≥ 40% | E16: =COUNTIFS('New Prices'!$R:$R,A16,'New Prices'!$C:$C,"<>Variant") -> 30 | F16: =SUMIFS('New Prices'!$K:$K,'New Prices'!$R:$R,A16,'New Prices'!$K:$K,">0") -> 2234854.5 | G16: =IF($F$18=0,0,F16/$F$18) -> 0.20503819 | H16: =G16*C16 -> 0.030755729
A17: 5 | B17: Group 5 | C17: 0.02 | D17: Price-sensitive best sellers: among 40 most-ordered, price < 50 EGP, margin ≥ 40% | E17: =COUNTIFS('New Prices'!$R:$R,A17,'New Prices'!$C:$C,"<>Variant") -> 23 | F17: =SUMIFS('New Prices'!$K:$K,'New Prices'!$R:$R,A17,'New Prices'!$K:$K,">0") -> 379075.38 | G17: =IF($F$18=0,0,F17/$F$18) -> 0.03477852 | H17: =G17*C17 -> 0.0006955704
A18: TOTAL | E18: =SUM(E13:E17) -> 1222 | F18: =SUM(F13:F17) -> 10899698 | G18: =SUM(G13:G17) -> 1
A21: Weighted average actual increase after rounding | B21: =IFERROR(SUMPRODUCT(('New Prices'!$R$5:$R$1281<>"-")*('New Prices'!$K$5:$K$1281>0)*'New Prices'!$K$5:$K$1281*'New Prices'!$V$5:$V$1281)/SUMPRODUCT(('New Prices'!$R$5:$R$1281<>"-")*('New Prices'!$K$5:$K$1281>0)*'New Prices'!$K$5:$K$1281),0) -> 0.17168805
A22: Target (currency increase) | B22: =B9 -> 0.1792
A23: Status | B23: =IF(B21>=B22,"✔ Target reached","✖ Below target – raise group %") -> ✖ Below target – raise group %
A25: Edit only the yellow cells. Every price in "New Prices" updates automatically.

Sheet New Prices
A1: Tamwenat Elzekrayat – New Prices by Price Group
A2: Sales period: 1 Jan – 22 Oct 2026 | Currency: EGP | Ranked by units sold | Current prices as in Shopify on 22 Oct 2026 (after wholesale fix)
A4: Rank | B4: Product | C4: Type | D4: Linked single / wholesale | E4: Status | F4: Units Sold | G4: Orders | H4: Gross Sales | I4: Discounts | J4: Returns | K4: Net Revenue | L4: % of Total Revenue | M4: Avg Net Price / Unit | N4: Current Price | O4: Cost in Shopify | P4: Unit Cost (EGP) | Q4: Current Margin | R4: Price Group | S4: Increase % | T4: New Price | U4: New Margin | V4: Actual Increase | W4: Reason
A5: 1 | B5: AlBaik meals | C5: Single | E5: Active | F5: 3695 | G5: 832 | H5: 1518355.2 | I5: -8260.48 | J5: -35101.2 | K5: =H5+I5+J5 -> 1474993.5 | L5: =IF($K$1282=0,0,K5/$K$1282) -> 0.12218616 | M5: =IF(F5<=0,0,K5/F5) -> 399.18633 | Q5: =IF(OR(N5="",P5=""),"",(N5-P5)/N5) | R5: 1 | S5: ='Price Groups'!$C$11 -> 0.15344828 | T5: =IF(OR(N5="",R5="-"),"",CEILING(ROUND(N5*(1+S5),2),IF(N5*(1+S5)<100,0.5,IF(N5*(1+S5)<1000,1,5)))) | U5: =IF(OR(T5="",P5=""),"",(T5-P5)/T5) | V5: =IFERROR(AVERAGE(V6:V31),0) -> 0.15512664 | W5: Custom increase set by user: meal 580 → 669 (+15.3%), same % on all AlBaik items. Cost 370 moves with the riyal → ≈436 today
B6: ↳ Spicy 4 pcs broasted chicken | C6: Variant | D6: AlBaik meals | K6: 0 | N6: 580 | P6: ='Price Groups'!$B$10*'Price Groups'!$B$8/'Price Groups'!$B$7 -> 436.304 | Q6: =IF(OR(N6="",P6=""),"",(N6-P6)/N6) -> 0.24775172 | R6: =R5 -> 1 | S6: ='Price Groups'!$C$11 -> 0.15344828 | T6: =IF(OR(N6="",R6="-"),"",CEILING(ROUND(N6*(1+S6),2),IF(N6*(1+S6)<100,0.5,IF(N6*(1+S6)<1000,1,5)))) -> 669 | U6: =IF(OR(T6="",P6=""),"",(T6-P6)/T6) -> 0.34782661 | V6: =IF(T6="",0,T6/N6-1) -> 0.15344828 | W6: Variant – same group as the product
B7: ↳ Regular 4 pcs broasted chicken | C7: Variant | D7: AlBaik meals | K7: 0 | N7: 580 | P7: ='Price Groups'!$B$10*'Price Groups'!$B$8/'Price Groups'!$B$7 -> 436.304 | Q7: =IF(OR(N7="",P7=""),"",(N7-P7)/N7) -> 0.24775172 | R7: =R5 -> 1 | S7: ='Price Groups'!$C$11 -> 0.15344828 | T7: =IF(OR(N7="",R7="-"),"",CEILING(ROUND(N7*(1+S7),2),IF(N7*(1+S7)<100,0.5,IF(N7*(1+S7)<1000,1,5)))) -> 669 | U7: =IF(OR(T7="",P7=""),"",(T7-P7)/T7) -> 0.34782661 | V7: =IF(T7="",0,T7/N7-1) -> 0.15344828 | W7: Variant – same group as the product
B8: ↳ Spicy 10 pcs mesahhab | C8: Variant | D8: AlBaik meals | K8: 0 | N8: 580 | P8: ='Price Groups'!$B$10*'Price Groups'!$B$8/'Price Groups'!$B$7 -> 436.304 | Q8: =IF(OR(N8="",P8=""),"",(N8-P8)/N8) -> 0.24775172 | R8: =R5 -> 1 | S8: ='Price Groups'!$C$11 -> 0.15344828 | T8: =IF(OR(N8="",R8="-"),"",CEILING(ROUND(N8*(1+S8),2),IF(N8*(1+S8)<100,0.5,IF(N8*(1+S8)<1000,1,5)))) -> 669 | U8: =IF(OR(T8="",P8=""),"",(T8-P8)/T8) -> 0.34782661 | V8: =IF(T8="",0,T8/N8-1) -> 0.15344828 | W8: Variant – same group as the product
B9: ↳ Regular 10 pcs mesahhab | C9: Variant | D9: AlBaik meals | K9: 0 | N9: 580 | P9: ='Price Groups'!$B$10*'Price Groups'!$B$8/'Price Groups'!$B$7 -> 436.304 | Q9: =IF(OR(N9="",P9=""),"",(N9-P9)/N9) -> 0.24775172 | R9: =R5 -> 1 | S9: ='Price Groups'!$C$11 -> 0.15344828 | T9: =IF(OR(N9="",R9="-"),"",CEILING(ROUND(N9*(1+S9),2),IF(N9*(1+S9)<100,0.5,IF(N9*(1+S9)<1000,1,5)))) -> 669 | U9: =IF(OR(T9="",P9=""),"",(T9-P9)/T9) -> 0.34782661 | V9: =IF(T9="",0,T9/N9-1) -> 0.15344828 | W9: Variant – same group as the product
B10: ↳ Big Baik regular | C10: Variant | D10: AlBaik meals | K10: 0 | N10: 420 | O10: 270 | P10: =O10*'Price Groups'!$B$8/'Price Groups'!$B$7 -> 318.384 | Q10: =IF(OR(N10="",P10=""),"",(N10-P10)/N10) -> 0.24194286 | R10: =R5 -> 1 | S10: ='Price Groups'!$C$11 -> 0.15344828 | T10: =IF(OR(N10="",R10="-"),"",CEILING(ROUND(N10*(1+S10),2),IF(N10*(1+S10)<100,0.5,IF(N10*(1+S10)<1000,1,5)))) -> 485 | U10: =IF(OR(T10="",P10=""),"",(T10-P10)/T10) -> 0.34353814 | V10: =IF(T10="",0,T10/N10-1) -> 0.1547619 | W10: Variant – same group as the product
B11: ↳ Big Baik regular + cheese | C11: Variant | D11: AlBaik meals | K11: 0 | N11: 480 | Q11: =IF(OR(N11="",P11=""),"",(N11-P11)/N11) | R11: =R5 -> 1 | S11: ='Price Groups'!$C$11 -> 0.15344828 | T11: =IF(OR(N11="",R11="-"),"",CEILING(ROUND(N11*(1+S11),2),IF(N11*(1+S11)<100,0.5,IF(N11*(1+S11)<1000,1,5)))) -> 554 | U11: =IF(OR(T11="",P11=""),"",(T11-P11)/T11) | V11: =IF(T11="",0,T11/N11-1) -> 0.15416667 | W11: Variant – same group as the product
B12: ↳ Big Baik spicy | C12: Variant | D12: AlBaik meals | K12: 0 | N12: 420 | O12: 270 | P12: =O12*'Price Groups'!$B$8/'Price Groups'!$B$7 -> 318.384 | Q12: =IF(OR(N12="",P12=""),"",(N12-P12)/N12) -> 0.24194286 | R12: =R5 -> 1 | S12: ='Price Groups'!$C$11 -> 0.15344828 | T12: =IF(OR(N12="",R12="-"),"",CEILING(ROUND(N12*(1+S12),2),IF(N12*(1+S12)<100,0.5,IF(N12*(1+S12)<1000,1,5)))) -> 485 | U12: =IF(OR(T12="",P12=""),"",(T12-P12)/T12) -> 0.34353814 | V12: =IF(T12="",0,T12/N12-1) -> 0.1547619 | W12: Variant – same group as the product
B13: ↳ Big Baik Spicy +cheese | C13: Variant | D13: AlBaik meals | K13: 0 | N13: 480 | Q13: =IF(OR(N13="",P13=""),"",(N13-P13)/N13) | R13: =R5 -> 1 | S13: ='Price Groups'!$C$11 -> 0.15344828 | T13: =IF(OR(N13="",R13="-"),"",CEILING(ROUND(N13*(1+S13),2),IF(N13*(1+S13)<100,0.5,IF(N13*(1+S13)<1000,1,5)))) -> 554 | U13: =IF(OR(T13="",P13=""),"",(T13-P13)/T13) | V13: =IF(T13="",0,T13/N13-1) -> 0.15416667 | W13: Variant – same group as the product
B14: ↳ extra cocktail sauce | C14: Variant | D14: AlBaik meals | K14: 0 | N14: 65 | O14: 25 | P14: =O14*'Price Groups'!$B$8/'Price Groups'!$B$7 -> 29.48 | Q14: =IF(OR(N14="",P14=""),"",(N14-P14)/N14) -> 0.54646154 | R14: =R5 -> 1 | S14: ='Price Groups'!$C$11 -> 0.15344828 | T14: =IF(OR(N14="",R14="-"),"",CEILING(ROUND(N14*(1+S14),2),IF(N14*(1+S14)<100,0.5,IF(N14*(1+S14)<1000,1,5)))) -> 75 | U14: =IF(OR(T14="",P14=""),"",(T14-P14)/T14) -> 0.60693333 | V14: =IF(T14="",0,T14/N14-1) -> 0.15384615 | W14: Variant – same group as the product
B15: ↳ extra garlic sauce | C15: Variant | D15: AlBaik meals | K15: 0 | N15: 65 | O15: 25 | P15: =O15*'Price Groups'!$B$8/'Price Groups'!$B$7 -> 29.48 | Q15: =IF(OR(N15="",P15=""),"",(N15-P15)/N15) -> 0.54646154 | R15: =R5 -> 1 | S15: ='Price Groups'!$C$11 -> 0.15344828 | T15: =IF(OR(N15="",R15="-"),"",CEILING(ROUND(N15*(1+S15),2),IF(N15*(1+S15)<100,0.5,IF(N15*(1+S15)<1000,1,5)))) -> 75 | U15: =IF(OR(T15="",P15=""),"",(T15-P15)/T15) -> 0.60693333 | V15: =IF(T15="",0,T15/N15-1) -> 0.15384615 | W15: Variant – same group as the product
B16: ↳ extra Mesahhab sauce | C16: Variant | D16: AlBaik meals | K16: 0 | N16: 65 | O16: 10 | P16: =O16*'Price Groups'!$B$8/'Price Groups'!$B$7 -> 11.792 | Q16: =IF(OR(N16="",P16=""),"",(N16-P16)/N16) -> 0.81858462 | R16: =R5 -> 1 | S16: ='Price Groups'!$C$11 -> 0.15344828 | T16: =IF(OR(N16="",R16="-"),"",CEILING(ROUND(N16*(1+S16),2),IF(N16*(1+S16)<100,0.5,IF(N16*(1+S16)<1000,1,5)))) -> 75 | U16: =IF(OR(T16="",P16=""),"",(T16-P16)/T16) -> 0.84277333 | V16: =IF(T16="",0,T16/N16-1) -> 0.15384615 | W16: Variant – same group as the product
B17: ↳ Shawarma sandwich with garlic sauce spaicy | C17: Variant | D17: AlBaik meals | K17: 0 | N17: 240 | Q17: =IF(OR(N17="",P17=""),"",(N17-P17)/N17) | R17: =R5 -> 1 | S17: ='Price Groups'!$C$11 -> 0.15344828 | T17: =IF(OR(N17="",R17="-"),"",CEILING(ROUND(N17*(1+S17),2),IF(N17*(1+S17)<100,0.5,IF(N17*(1+S17)<1000,1,5)))) -> 277 | U17: =IF(OR(T17="",P17=""),"",(T17-P17)/T17) | V17: =IF(T17="",0,T17/N17-1) -> 0.15416667 | W17: Variant – same group as the product
B18: ↳ Shawarma sandwich with garlic sauce | C18: Variant | D18: AlBaik meals | K18: 0 | N18: 240 | Q18: =IF(OR(N18="",P18=""),"",(N18-P18)/N18) | R18: =R5 -> 1 | S18: ='Price Groups'!$C$11 -> 0.15344828 | T18: =IF(OR(N18="",R18="-"),"",CEILING(ROUND(N18*(1+S18),2),IF(N18*(1+S18)<100,0.5,IF(N18*(1+S18)<1000,1,5)))) -> 277 | U18: =IF(OR(T18="",P18=""),"",(T18-P18)/T18) | V18: =IF(T18="",0,T18/N18-1) -> 0.15416667 | W18: Variant – same group as the product
B19: ↳ Regular Fish fillet burger sandwich | C19: Variant | D19: AlBaik meals | K19: 0 | N19: 210 | Q19: =IF(OR(N19="",P19=""),"",(N19-P19)/N19) | R19: =R5 -> 1 | S19: ='Price Groups'!$C$11 -> 0.15344828 | T19: =IF(OR(N19="",R19="-"),"",CEILING(ROUND(N19*(1+S19),2),IF(N19*(1+S19)<100,0.5,IF(N19*(1+S19)<1000,1,5)))) -> 243 | U19: =IF(OR(T19="",P19=""),"",(T19-P19)/T19) | V19: =IF(T19="",0,T19/N19-1) -> 0.15714286 | W19: Variant – same group as the product
B20: ↳ spicy Super baik Shrimp sandwich | C20: Variant | D20: AlBaik meals | K20: 0 | N20: 590 | Q20: =IF(OR(N20="",P20=""),"",(N20-P20)/N20) | R20: =R5 -> 1 | S20: ='Price Groups'!$C$11 -> 0.15344828 | T20: =IF(OR(N20="",R20="-"),"",CEILING(ROUND(N20*(1+S20),2),IF(N20*(1+S20)<100,0.5,IF(N20*(1+S20)<1000,1,5)))) -> 681 | U20: =IF(OR(T20="",P20=""),"",(T20-P20)/T20) | V20: =IF(T20="",0,T20/N20-1) -> 0.15423729 | W20: Variant – same group as the product
B21: ↳ Regular Fish fillet meal 6pcs | C21: Variant | D21: AlBaik meals | K21: 0 | N21: 570 | Q21: =IF(OR(N21="",P21=""),"",(N21-P21)/N21) | R21: =R5 -> 1 | S21: ='Price Groups'!$C$11 -> 0.15344828 | T21: =IF(OR(N21="",R21="-"),"",CEILING(ROUND(N21*(1+S21),2),IF(N21*(1+S21)<100,0.5,IF(N21*(1+S21)<1000,1,5)))) -> 658 | U21: =IF(OR(T21="",P21=""),"",(T21-P21)/T21) | V21: =IF(T21="",0,T21/N21-1) -> 0.15438596 | W21: Variant – same group as the product
B22: ↳ Regular fish fillet sandwich | C22: Variant | D22: AlBaik meals | K22: 0 | N22: 260 | Q22: =IF(OR(N22="",P22=""),"",(N22-P22)/N22) | R22: =R5 -> 1 | S22: ='Price Groups'!$C$11 -> 0.15344828 | T22: =IF(OR(N22="",R22="-"),"",CEILING(ROUND(N22*(1+S22),2),IF(N22*(1+S22)<100,0.5,IF(N22*(1+S22)<1000,1,5)))) -> 300 | U22: =IF(OR(T22="",P22=""),"",(T22-P22)/T22) | V22: =IF(T22="",0,T22/N22-1) -> 0.15384615 | W22: Variant – same group as the product
B23: ↳ spicy fish fillet sandwich | C23: Variant | D23: AlBaik meals | K23: 0 | N23: 280.8 | Q23: =IF(OR(N23="",P23=""),"",(N23-P23)/N23) | R23: =R5 -> 1 | S23: ='Price Groups'!$C$11 -> 0.15344828 | T23: =IF(OR(N23="",R23="-"),"",CEILING(ROUND(N23*(1+S23),2),IF(N23*(1+S23)<100,0.5,IF(N23*(1+S23)<1000,1,5)))) -> 324 | U23: =IF(OR(T23="",P23=""),"",(T23-P23)/T23) | V23: =IF(T23="",0,T23/N23-1) -> 0.15384615 | W23: Variant – same group as the product
B24: ↳ spicy Fish fillet meal 10pcs | C24: Variant | D24: AlBaik meals | K24: 0 | N24: 749 | Q24: =IF(OR(N24="",P24=""),"",(N24-P24)/N24) | R24: =R5 -> 1 | S24: ='Price Groups'!$C$11 -> 0.15344828 | T24: =IF(OR(N24="",R24="-"),"",CEILING(ROUND(N24*(1+S24),2),IF(N24*(1+S24)<100,0.5,IF(N24*(1+S24)<1000,1,5)))) -> 864 | U24: =IF(OR(T24="",P24=""),"",(T24-P24)/T24) | V24: =IF(T24="",0,T24/N24-1) -> 0.15353805 | W24: Variant – same group as the product
B25: ↳ 10 Piece spicy economy Shrimp Meal | C25: Variant | D25: AlBaik meals | K25: 0 | N25: 730 | Q25: =IF(OR(N25="",P25=""),"",(N25-P25)/N25) | R25: =R5 -> 1 | S25: ='Price Groups'!$C$11 -> 0.15344828 | T25: =IF(OR(N25="",R25="-"),"",CEILING(ROUND(N25*(1+S25),2),IF(N25*(1+S25)<100,0.5,IF(N25*(1+S25)<1000,1,5)))) -> 843 | U25: =IF(OR(T25="",P25=""),"",(T25-P25)/T25) | V25: =IF(T25="",0,T25/N25-1) -> 0.15479452 | W25: Variant – same group as the product
B26: ↳ Regular suber baik Shrimp sandwich | C26: Variant | D26: AlBaik meals | K26: 0 | N26: 595 | Q26: =IF(OR(N26="",P26=""),"",(N26-P26)/N26) | R26: =R5 -> 1 | S26: ='Price Groups'!$C$11 -> 0.15344828 | T26: =IF(OR(N26="",R26="-"),"",CEILING(ROUND(N26*(1+S26),2),IF(N26*(1+S26)<100,0.5,IF(N26*(1+S26)<1000,1,5)))) -> 687 | U26: =IF(OR(T26="",P26=""),"",(T26-P26)/T26) | V26: =IF(T26="",0,T26/N26-1) -> 0.15462185 | W26: Variant – same group as the product
B27: ↳ Albaik Shrimp Economy Meal 10 piece | C27: Variant | D27: AlBaik meals | K27: 0 | N27: 730 | Q27: =IF(OR(N27="",P27=""),"",(N27-P27)/N27) | R27: =R5 -> 1 | S27: ='Price Groups'!$C$11 -> 0.15344828 | T27: =IF(OR(N27="",R27="-"),"",CEILING(ROUND(N27*(1+S27),2),IF(N27*(1+S27)<100,0.5,IF(N27*(1+S27)<1000,1,5)))) -> 843 | U27: =IF(OR(T27="",P27=""),"",(T27-P27)/T27) | V27: =IF(T27="",0,T27/N27-1) -> 0.15479452 | W27: Variant – same group as the product
B28: ↳ 10 Piece Regular Jumbo Shrimp Meal | C28: Variant | D28: AlBaik meals | K28: 0 | N28: 890 | Q28: =IF(OR(N28="",P28=""),"",(N28-P28)/N28) | R28: =R5 -> 1 | S28: ='Price Groups'!$C$11 -> 0.15344828 | T28: =IF(OR(N28="",R28="-"),"",CEILING(ROUND(N28*(1+S28),2),IF(N28*(1+S28)<100,0.5,IF(N28*(1+S28)<1000,1,5)))) -> 1030 | U28: =IF(OR(T28="",P28=""),"",(T28-P28)/T28) | V28: =IF(T28="",0,T28/N28-1) -> 0.15730337 | W28: Variant – same group as the product
B29: ↳ Regular super baik grilled chicken | C29: Variant | D29: AlBaik meals | K29: 0 | N29: 560 | Q29: =IF(OR(N29="",P29=""),"",(N29-P29)/N29) | R29: =R5 -> 1 | S29: ='Price Groups'!$C$11 -> 0.15344828 | T29: =IF(OR(N29="",R29="-"),"",CEILING(ROUND(N29*(1+S29),2),IF(N29*(1+S29)<100,0.5,IF(N29*(1+S29)<1000,1,5)))) -> 646 | U29: =IF(OR(T29="",P29=""),"",(T29-P29)/T29) | V29: =IF(T29="",0,T29/N29-1) -> 0.15357143 | W29: Variant – same group as the product
B30: ↳ spicy super baik grilled chicken | C30: Variant | D30: AlBaik meals | K30: 0 | N30: 604.8 | Q30: =IF(OR(N30="",P30=""),"",(N30-P30)/N30) | R30: =R5 -> 1 | S30: ='Price Groups'!$C$11 -> 0.15344828 | T30: =IF(OR(N30="",R30="-"),"",CEILING(ROUND(N30*(1+S30),2),IF(N30*(1+S30)<100,0.5,IF(N30*(1+S30)<1000,1,5)))) -> 698 | U30: =IF(OR(T30="",P30=""),"",(T30-P30)/T30) | V30: =IF(T30="",0,T30/N30-1) -> 0.15410053 | W30: Variant – same group as the product
B31: ↳ ALBAIK Maamoul 2pieces | C31: Variant | D31: AlBaik meals | K31: 0 | N31: 19.99 | Q31: =IF(OR(N31="",P31=""),"",(N31-P31)/N31) | R31: =R5 -> 1 | S31: ='Price Groups'!$C$11 -> 0.15344828 | T31: =IF(OR(N31="",R31="-"),"",CEILING(ROUND(N31*(1+S31),2),IF(N31*(1+S31)<100,0.5,IF(N31*(1+S31)<1000,1,5)))) -> 23.5 | U31: =IF(OR(T31="",P31=""),"",(T31-P31)/T31) | V31: =IF(T31="",0,T31/N31-1) -> 0.17558779 | W31: Variant – same group as the product
A32: 2 | B32: Oman Chips spicy small pack | C32: Single | E32: Active | F32: 1414 | G32: 485 | H32: 67674.49 | I32: -401.61 | J32: -5567.47 | K32: =H32+I32+J32 -> 61705.41 | L32: =IF($K$1282=0,0,K32/$K$1282) -> 0.0051115798 | M32: =IF(F32<=0,0,K32/F32) -> 43.638904 | N32: 44.99 | O32: 0.77 | P32: =O32*'Price Groups'!$B$5 -> 17.325 | Q32: =IF(OR(N32="",P32=""),"",(N32-P32)/N32) -> 0.61491443 | R32: 5 | S32: =IF(R32="-",0,IFERROR(VLOOKUP(R32,'Price Groups'!$A$13:$C$17,3,FALSE()),0)) -> 0.02 | T32: =IF(OR(N32="",R32="-"),"",CEILING(ROUND(N32*(1+S32),2),IF(N32*(1+S32)<100,0.5,IF(N32*(1+S32)<1000,1,5)))) -> 46 | U32: =IF(OR(T32="",P32=""),"",(T32-P32)/T32) -> 0.62336957 | V32: =IF(T32="",0,T32/N32-1) -> 0.022449433 | W32: Price-sensitive best seller (frequent, cheap, high margin) – protect price image
A33: 3 | B33: special order | C33: - | E33: Active | F33: 1093 | G33: 143 | H33: 1140000 | I33: -63960.92 | J33: -46215 | K33: =H33+I33+J33 -> 1029824.1 | L33: =IF($K$1282=0,0,K33/$K$1282) -> 0.085309018 | M33: =IF(F33<=0,0,K33/F33) -> 942.19952 | N33: 1000 | Q33: =IF(OR(N33="",P33=""),"",(N33-P33)/N33) | R33: - | S33: =IF(R33="-",0,IFERROR(VLOOKUP(R33,'Price Groups'!$A$13:$C$17,3,FALSE()),0)) -> 0 | T33: =IF(OR(N33="",R33="-"),"",CEILING(ROUND(N33*(1+S33),2),IF(N33*(1+S33)<100,0.5,IF(N33*(1+S33)<1000,1,5)))) | U33: =IF(OR(T33="",P33=""),"",(T33-P33)/T33) | V33: =IF(T33="",0,T33/N33-1) -> 0 | W33: Not repriced – not a catalog product
A34: 4 | B34: Gandour Mastic Gum, One Piece, 2.7 Grams | C34: Single | E34: Active | F34: 1002 | G34: 90 | H34: 6942.1 | I34: -51.56 | J34: -702.4 | K34: =H34+I34+J34 -> 6188.14 | L34: =IF($K$1282=0,0,K34/$K$1282) -> 0.00051261585 | M34: =IF(F34<=0,0,K34/F34) -> 6.1757884 | N34: 12 | O34: 0.12 | P34: =O34*'Price Groups'!$B$5 -> 2.7 | Q34: =IF(OR(N34="",P34=""),"",(N34-P34)/N34) -> 0.775 | R34: 1 | S34: =IF(R34="-",0,IFERROR(VLOOKUP(R34,'Price Groups'!$A$13:$C$17,3,FALSE()),0)) -> 0.22 | T34: =IF(OR(N34="",R34="-"),"",CEILING(ROUND(N34*(1+S34),2),IF(N34*(1+S34)<100,0.5,IF(N34*(1+S34)<1000,1,5)))) -> 15 | U34: =IF(OR(T34="",P34=""),"",(T34-P34)/T34) -> 0.82 | V34: =IF(T34="",0,T34/N34-1) -> 0.25 | W34: Slow mover / long tail – low price sensitivity
A35: 5 | B35: Ghandour MESTEKA Gum 6 Pcs Pack | C35: Single | E35: Active | F35: 985 | G35: 323 | H35: 33223.77 | I35: -202.78 | J35: -4064.74 | K35: =H35+I35+J35 -> 28956.25 | L35: =IF($K$1282=0,0,K35/$K$1282) -> 0.0023986905 | M35: =IF(F35<=0,0,K35/F35) -> 29.397208 | N35: 30 | O35: 0.43 | P35: =O35*'Price Groups'!$B$5 -> 9.675 | Q35: =IF(OR(N35="",P35=""),"",(N35-P35)/N35) -> 0.6775 | R35: 5 | S35: =IF(R35="-",0,IFERROR(VLOOKUP(R35,'Price Groups'!$A$13:$C$17,3,FALSE()),0)) -> 0.02 | T35: =IF(OR(N35="",R35="-"),"",CEILING(ROUND(N35*(1+S35),2),IF(N35*(1+S35)<100,0.5,IF(N35*(1+S35)<1000,1,5)))) -> 31 | U35: =IF(OR(T35="",P35=""),"",(T35-P35)/T35) -> 0.68790323 | V35: =IF(T35="",0,T35/N35-1) -> 0.033333333 | W35: Price-sensitive best seller (frequent, cheap, high margin) – protect price image
A36: 6 | B36: Mirinda citrus | C36: Single | D36: Mirinda citrus 24pack | E36: Active | F36: 979 | G36: 439 | H36: 108001.82 | I36: -781.47 | J36: -12827.29 | K36: =H36+I36+J36 -> 94393.06 | L36: =IF($K$1282=0,0,K36/$K$1282) -> 0.0078193736 | M36: =IF(F36<=0,0,K36/F36) -> 96.417835 | N36: 95 | O36: 1.82 | P36: =O36*'Price Groups'!$B$5 -> 40.95 | Q36: =IF(OR(N36="",P36=""),"",(N36-P36)/N36) -> 0.56894737 | R36: 2 | S36: =IF(R36="-",0,IFERROR(VLOOKUP(R36,'Price Groups'!$A$13:$C$17,3,FALSE()),0)) -> 0.18 | T36: =IF(OR(N36="",R36="-"),"",CEILING(ROUND(N36*(1+S36),2),IF(N36*(1+S36)<100,0.5,IF(N36*(1+S36)<1000,1,5)))) -> 113 | U36: =IF(OR(T36="",P36=""),"",(T36-P36)/T36) -> 0.63761062 | V36: =IF(T36="",0,T36/N36-1) -> 0.18947368 | W36: Core seller, medium margin (40%)
A37: 7 | B37: (No product title – custom/manual items) | C37: - | E37: - | F37: 958 | G37: 549 | H37: 167784.68 | I37: -783.11 | J37: -24769.39 | K37: =H37+I37+J37 -> 142232.18 | L37: =IF($K$1282=0,0,K37/$K$1282) -> 0.011782292 | M37: =IF(F37<=0,0,K37/F37) -> 148.46783 | Q37: =IF(OR(N37="",P37=""),"",(N37-P37)/N37) | R37: - | S37: =IF(R37="-",0,IFERROR(VLOOKUP(R37,'Price Groups'!$A$13:$C$17,3,FALSE()),0)) -> 0 | T37: =IF(OR(N37="",R37="-"),"",CEILING(ROUND(N37*(1+S37),2),IF(N37*(1+S37)<100,0.5,IF(N37*(1+S37)<1000,1,5)))) | U37: =IF(OR(T37="",P37=""),"",(T37-P37)/T37) | V37: =IF(T37="",0,T37/N37-1) -> 0 | W37: Not repriced – not a catalog product
A38: 8 | B38: zamzam water 330ml | C38: Single | E38: Active | F38: 918 | G38: 300 | H38: 135592.18 | I38: -1177.3 | J38: -13082.09 | K38: =H38+I38+J38 -> 121332.79 | L38: =IF($K$1282=0,0,K38/$K$1282) -> 0.010051019 | M38: =IF(F38<=0,0,K38/F38) -> 132.1708 | N38: 149.99 | O38: 2.61 | P38: =O38*'Price Groups'!$B$5 -> 58.725 | Q38: =IF(OR(N38="",P38=""),"",(N38-P38)/N38) -> 0.6084739 | R38: 4 | S38: =IF(R38="-",0,IFERROR(VLOOKUP(R38,'Price Groups'!$A$13:$C$17,3,FALSE()),0)) -> 0.15 | T38: =IF(OR(N38="",R38="-"),"",CEILING(ROUND(N38*(1+S38),2),IF(N38*(1+S38)<100,0.5,IF(N38*(1+S38)<1000,1,5)))) -> 173 | U38: =IF(OR(T38="",P38=""),"",(T38-P38)/T38) -> 0.66054913 | V38: =IF(T38="",0,T38/N38-1) -> 0.15341023 | W38: Top revenue item with healthy margin
A39: 9 | B39: Zamzam water | C39: Single | E39: Active | F39: 831 | G39: 532 | H39: 645690.36 | I39: -10020.76 | J39: -42697.4 | K39: =H39+I39+J39 -> 592972.2 | L39: =IF($K$1282=0,0,K39/$K$1282) -> 0.049120891 | M39: =IF(F39<=0,0,K39/F39) -> 713.56462 | Q39: =IF(OR(N39="",P39=""),"",(N39-P39)/N39) | R39: 4 | S39: =IF(R39="-",0,IFERROR(VLOOKUP(R39,'Price Groups'!$A$13:$C$17,3,FALSE()),0)) -> 0.15 | T39: =IF(OR(N39="",R39="-"),"",CEILING(ROUND(N39*(1+S39),2),IF(N39*(1+S39)<100,0.5,IF(N39*(1+S39)<1000,1,5)))) | U39: =IF(OR(T39="",P39=""),"",(T39-P39)/T39) | V39: =IFERROR(AVERAGE(V40:V42),0) -> 0.1539267 | W39: Top revenue item with healthy margin
B40: ↳ 5 liters without cartoon | C40: Variant | D40: Zamzam water | K40: 0 | N40: 885 | O40: 13.8 | P40: =O40*'Price Groups'!$B$5 -> 310.5 | Q40: =IF(OR(N40="",P40=""),"",(N40-P40)/N40) -> 0.64915254 | R40: =R39 -> 4 | S40: =IF(R40="-",0,IFERROR(VLOOKUP(R40,'Price Groups'!$A$13:$C$17,3,FALSE()),0)) -> 0.15 | T40: =IF(OR(N40="",R40="-"),"",CEILING(ROUND(N40*(1+S40),2),IF(N40*(1+S40)<100,0.5,IF(N40*(1+S40)<1000,1,5)))) -> 1020 | U40: =IF(OR(T40="",P40=""),"",(T40-P40)/T40) -> 0.69558824 | V40: =IF(T40="",0,T40/N40-1) -> 0.15254237 | W40: Variant – same group as the product
B41: ↳ 5 liters with cartoon | C41: Variant | D41: Zamzam water | K41: 0 | N41: 950 | O41: 13.8 | P41: =O41*'Price Groups'!$B$5 -> 310.5 | Q41: =IF(OR(N41="",P41=""),"",(N41-P41)/N41) -> 0.67315789 | R41: =R39 -> 4 | S41: =IF(R41="-",0,IFERROR(VLOOKUP(R41,'Price Groups'!$A$13:$C$17,3,FALSE()),0)) -> 0.15 | T41: =IF(OR(N41="",R41="-"),"",CEILING(ROUND(N41*(1+S41),2),IF(N41*(1+S41)<100,0.5,IF(N41*(1+S41)<1000,1,5)))) -> 1095 | U41: =IF(OR(T41="",P41=""),"",(T41-P41)/T41) -> 0.71643836 | V41: =IF(T41="",0,T41/N41-1) -> 0.15263158 | W41: Variant – same group as the product
B42: ↳ 200 ml | C42: Variant | D42: Zamzam water | K42: 0 | N42: 118.45 | O42: 13.8 | P42: =O42*'Price Groups'!$B$5 -> 310.5 | Q42: =IF(OR(N42="",P42=""),"",(N42-P42)/N42) -> -1.6213592 | R42: =R39 -> 4 | S42: =IF(R42="-",0,IFERROR(VLOOKUP(R42,'Price Groups'!$A$13:$C$17,3,FALSE()),0)) -> 0.15 | T42: =IF(OR(N42="",R42="-"),"",CEILING(ROUND(N42*(1+S42),2),IF(N42*(1+S42)<100,0.5,IF(N42*(1+S42)<1000,1,5)))) -> 137 | U42: =IF(OR(T42="",P42=""),"",(T42-P42)/T42) -> -1.2664234 | V42: =IF(T42="",0,T42/N42-1) -> 0.15660616 | W42: Variant – same group as the product
A43: 10 | B43: Ulker choco sandwich | C43: Single | E43: Active | F43: 769 | G43: 167 | H43: 37623.83 | I43: -5563.83 | J43: -2590.96 | K43: =H43+I43+J43 -> 29469.04 | L43: =IF($K$1282=0,0,K43/$K$1282) -> 0.0024411692 | M43: =IF(F43<=0,0,K43/F43) -> 38.321248 | N43: 55.37 | O43: 0.52 | P43: =O43*'Price Groups'!$B$5 -> 11.7 | Q43: =IF(OR(N43="",P43=""),"",(N43-P43)/N43) -> 0.78869424 | R43: 3 | S43: =IF(R43="-",0,IFERROR(VLOOKUP(R43,'Price Groups'!$A$13:$C$17,3,FALSE()),0)) -> 0.16 | T43: =IF(OR(N43="",R43="-"),"",CEILING(ROUND(N43*(1+S43),2),IF(N43*(1+S43)<100,0.5,IF(N43*(1+S43)<1000,1,5)))) -> 64.5 | U43: =IF(OR(T43="",P43=""),"",(T43-P43)/T43) -> 0.81860465 | V43: =IF(T43="",0,T43/N43-1) -> 0.16489074 | W43: Core seller with healthy margin
A44: 11 | B44: Millionaire cheese corn | C44: Single | E44: Active | F44: 766 | G44: 301 | H44: 16298.71 | I44: -86.79 | J44: -1885.64 | K44: =H44+I44+J44 -> 14326.28 | L44: =IF($K$1282=0,0,K44/$K$1282) -> 0.0011867667 | M44: =IF(F44<=0,0,K44/F44) -> 18.702715 | N44: 22 | O44: 0.36 | P44: =O44*'Price Groups'!$B$5 -> 8.1 | Q44: =IF(OR(N44="",P44=""),"",(N44-P44)/N44) -> 0.63181818 | R44: 5 | S44: =IF(R44="-",0,IFERROR(VLOOKUP(R44,'Price Groups'!$A$13:$C$17,3,FALSE()),0)) -> 0.02 | T44: =IF(OR(N44="",R44="-"),"",CEILING(ROUND(N44*(1+S44),2),IF(N44*(1+S44)<100,0.5,IF(N44*(1+S44)<1000,1,5)))) -> 22.5 | U44: =IF(OR(T44="",P44=""),"",(T44-P44)/T44) -> 0.64 | V44: =IF(T44="",0,T44/N44-1) -> 0.022727273 | W44: Price-sensitive best seller (frequent, cheap, high margin) – protect price image
A45: 12 | B45: Shani | C45: Single | E45: Active | F45: 681 | G45: 229 | H45: 72177.84 | I45: -2873.22 | J45: -4175.76 | K45: =H45+I45+J45 -> 65128.86 | L45: =IF($K$1282=0,0,K45/$K$1282) -> 0.005395173 | M45: =IF(F45<=0,0,K45/F45) -> 95.637093 | N45: 99 | O45: 2.34 | P45: =O45*'Price Groups'!$B$5 -> 52.65 | Q45: =IF(OR(N45="",P45=""),"",(N45-P45)/N45) -> 0.46818182 | R45: 4 | S45: =IF(R45="-",0,IFERROR(VLOOKUP(R45,'Price Groups'!$A$13:$C$17,3,FALSE()),0)) -> 0.15 | T45: =IF(OR(N45="",R45="-"),"",CEILING(ROUND(N45*(1+S45),2),IF(N45*(1+S45)<100,0.5,IF(N45*(1+S45)<1000,1,5)))) -> 114 | U45: =IF(OR(T45="",P45=""),"",(T45-P45)/T45) -> 0.53815789 | V45: =IF(T45="",0,T45/N45-1) -> 0.15151515 | W45: Top revenue item with healthy margin
A46: 13 | B46: cheetos har nar | C46: Single | D46: cheetos har nar 16 pack * 25g | E46: Active | F46: 678 | G46: 264 | H46: 28118 | I46: -177.49 | J46: -1965.35 | K46: =H46+I46+J46 -> 25975.16 | L46: =IF($K$1282=0,0,K46/$K$1282) -> 0.0021517417 | M46: =IF(F46<=0,0,K46/F46) -> 38.311445 | N46: 45 | O46: 1 | P46: =O46*'Price Groups'!$B$5 -> 22.5 | Q46: =IF(OR(N46="",P46=""),"",(N46-P46)/N46) -> 0.5 | R46: 5 | S46: =IF(R46="-",0,IFERROR(VLOOKUP(R46,'Price Groups'!$A$13:$C$17,3,FALSE()),0)) -> 0.02 | T46: =IF(OR(N46="",R46="-"),"",CEILING(ROUND(N46*(1+S46),2),IF(N46*(1+S46)<100,0.5,IF(N46*(1+S46)<1000,1,5)))) -> 46 | U46: =IF(OR(T46="",P46=""),"",(T46-P46)/T46) -> 0.51086957 | V46: =IF(T46="",0,T46/N46-1) -> 0.022222222 | W46: Price-sensitive best seller (frequent, cheap, high margin) – protect price image
A47: 14 | B47: batook mistic gum 1 pack | C47: Single | E47: Active | F47: 653 | G47: 79 | H47: 6407.72 | I47: -10.55 | J47: -683.87 | K47: =H47+I47+J47 -> 5713.3 | L47: =IF($K$1282=0,0,K47/$K$1282) -> 0.00047328085 | M47: =IF(F47<=0,0,K47/F47) -> 8.7493109 | N47: 9 | O47: 0.16 | P47: =O47*'Price Groups'!$B$5 -> 3.6 | Q47: =IF(OR(N47="",P47=""),"",(N47-P47)/N47) -> 0.6 | R47: 1 | S47: =IF(R47="-",0,IFERROR(VLOOKUP(R47,'Price Groups'!$A$13:$C$17,3,FALSE()),0)) -> 0.22 | T47: =IF(OR(N47="",R47="-"),"",CEILING(ROUND(N47*(1+S47),2),IF(N47*(1+S47)<100,0.5,IF(N47*(1+S47)<1000,1,5)))) -> 11 | U47: =IF(OR(T47="",P47=""),"",(T47-P47)/T47) -> 0.67272727 | V47: =IF(T47="",0,T47/N47-1) -> 0.22222222 | W47: Slow mover / long tail – low price sensitivity
A48: 15 | B48: nescafe arabiana with Cardamom 1 pac 30g | C48: Single | D48: nescafe arabiana with Cardamom 1 pac 30g 1 pack of 10 pcs | E48: Active | F48: 636 | G48: 206 | H48: 204445.59 | I48: -489.55 | J48: -21122.11 | K48: =H48+I48+J48 -> 182833.93 | L48: =IF($K$1282=0,0,K48/$K$1282) -> 0.015145677 | M48: =IF(F48<=0,0,K48/F48) -> 287.47473 | N48: 315.01 | O48: 7.6 | P48: =O48*'Price Groups'!$B$5 -> 171 | Q48: =IF(OR(N48="",P48=""),"",(N48-P48)/N48) -> 0.45716009 | R48: 2 | S48: =IF(R48="-",0,IFERROR(VLOOKUP(R48,'Price Groups'!$A$13:$C$17,3,FALSE()),0)) -> 0.18 | T48: =IF(OR(N48="",R48="-"),"",CEILING(ROUND(N48*(1+S48),2),IF(N48*(1+S48)<100,0.5,IF(N48*(1+S48)<1000,1,5)))) -> 372 | U48: =IF(OR(T48="",P48=""),"",(T48-P48)/T48) -> 0.54032258 | V48: =IF(T48="",0,T48/N48-1) -> 0.18091489 | W48: Core seller, medium margin (37%)
A49: 16 | B49: kinza citrus | C49: Single | E49: Active | F49: 635 | G49: 69 | H49: 53251.67 | I49: -4357.54 | J49: -947.96 | K49: =H49+I49+J49 -> 47946.17 | L49: =IF($K$1282=0,0,K49/$K$1282) -> 0.0039717858 | M49: =IF(F49<=0,0,K49/F49) -> 75.50578 | N49: 80 | O49: 1.74 | P49: =O49*'Price Groups'!$B$5 -> 39.15 | Q49: =IF(OR(N49="",P49=""),"",(N49-P49)/N49) -> 0.510625 | R49: 4 | S49: =IF(R49="-",0,IFERROR(VLOOKUP(R49,'Price Groups'!$A$13:$C$17,3,FALSE()),0)) -> 0.15 | T49: =IF(OR(N49="",R49="-"),"",CEILING(ROUND(N49*(1+S49),2),IF(N49*(1+S49)<100,0.5,IF(N49*(1+S49)<1000,1,5)))) -> 92 | U49: =IF(OR(T49="",P49=""),"",(T49-P49)/T49) -> 0.57445652 | V49: =IF(T49="",0,T49/N49-1) -> 0.15 | W49: Top revenue item with healthy margin
A50: 17 | B50: SOHAR chipsy 13g | C50: Single | D50: SOHAR chips 23pack *13g | E50: Active | F50: 611 | G50: 221 | H50: 28244.5 | I50: -547.67 | J50: -1424.91 | K50: =H50+I50+J50 -> 26271.92 | L50: =IF($K$1282=0,0,K50/$K$1282) -> 0.0021763248 | M50: =IF(F50<=0,0,K50/F50) -> 42.998232 | N50: 39.99 | O50: 0.78 | P50: =O50*'Price Groups'!$B$5 -> 17.55 | Q50: =IF(OR(N50="",P50=""),"",(N50-P50)/N50) -> 0.56114029 | R50: 5 | S50: =IF(R50="-",0,IFERROR(VLOOKUP(R50,'Price Groups'!$A$13:$C$17,3,FALSE()),0)) -> 0.02 | T50: =IF(OR(N50="",R50="-"),"",CEILING(ROUND(N50*(1+S50),2),IF(N50*(1+S50)<100,0.5,IF(N50*(1+S50)<1000,1,5)))) -> 41 | U50: =IF(OR(T50="",P50=""),"",(T50-P50)/T50) -> 0.57195122 | V50: =IF(T50="",0,T50/N50-1) -> 0.025256314 | W50: Price-sensitive best seller (frequent, cheap, high margin) – protect price image
A51: 18 | B51: chicken sticks Chips vegetables | C51: Single | E51: Active | F51: 590 | G51: 348 | H51: 25708.5 | I51: -253.99 | J51: -3024.68 | K51: =H51+I51+J51 -> 22429.83 | L51: =IF($K$1282=0,0,K51/$K$1282) -> 0.0018580521 | M51: =IF(F51<=0,0,K51/F51) -> 38.016661 | N51: 39.99 | O51: 0.49 | P51: =O51*'Price Groups'!$B$5 -> 11.025 | Q51: =IF(OR(N51="",P51=""),"",(N51-P51)/N51) -> 0.72430608 | R51: 5 | S51: =IF(R51="-",0,IFERROR(VLOOKUP(R51,'Price Groups'!$A$13:$C$17,3,FALSE()),0)) -> 0.02 | T51: =IF(OR(N51="",R51="-"),"",CEILING(ROUND(N51*(1+S51),2),IF(N51*(1+S51)<100,0.5,IF(N51*(1+S51)<1000,1,5)))) -> 41 | U51: =IF(OR(T51="",P51=""),"",(T51-P51)/T51) -> 0.73109756 | V51: =IF(T51="",0,T51/N51-1) -> 0.025256314 | W51: Price-sensitive best seller (frequent, cheap, high margin) – protect price image
A52: 19 | B52: ghandour cherry lolli pop | C52: Single | E52: Active | F52: 579 | G52: 85 | H52: 3312.69 | I52: -29.6 | J52: -234.88 | K52: =H52+I52+J52 -> 3048.21 | L52: =IF($K$1282=0,0,K52/$K$1282) -> 0.00025250895 | M52: =IF(F52<=0,0,K52/F52) -> 5.2646114 | N52: 6 | O52: 0.17 | P52: =O52*'Price Groups'!$B$5 -> 3.825 | Q52: =IF(OR(N52="",P52=""),"",(N52-P52)/N52) -> 0.3625 | R52: 1 | S52: =IF(R52="-",0,IFERROR(VLOOKUP(R52,'Price Groups'!$A$13:$C$17,3,FALSE()),0)) -> 0.22 | T52: =IF(OR(N52="",R52="-"),"",CEILING(ROUND(N52*(1+S52),2),IF(N52*(1+S52)<100,0.5,IF(N52*(1+S52)<1000,1,5)))) -> 7.5 | U52: =IF(OR(T52="",P52=""),"",(T52-P52)/T52) -> 0.49 | V52: =IF(T52="",0,T52/N52-1) -> 0.25 | W52: Slow mover / long tail – low price sensitivity
A53: 20 | B53: snack shrimp Flavored | C53: Single | E53: Active | F53: 577 | G53: 164 | H53: 11872.66 | I53: -105.22 | J53: -1822.22 | K53: =H53+I53+J53 -> 9945.22 | L53: =IF($K$1282=0,0,K53/$K$1282) -> 0.00082384649 | M53: =IF(F53<=0,0,K53/F53) -> 17.236083 | N53: 22 | O53: 0.31 | P53: =O53*'Price Groups'!$B$5 -> 6.975 | Q53: =IF(OR(N53="",P53=""),"",(N53-P53)/N53) -> 0.68295455 | R53: 1 | S53: =IF(R53="-",0,IFERROR(VLOOKUP(R53,'Price Groups'!$A$13:$C$17,3,FALSE()),0)) -> 0.22 | T53: =IF(OR(N53="",R53="-"),"",CEILING(ROUND(N53*(1+S53),2),IF(N53*(1+S53)<100,0.5,IF(N53*(1+S53)<1000,1,5)))) -> 27 | U53: =IF(OR(T53="",P53=""),"",(T53-P53)/T53) -> 0.74166667 | V53: =IF(T53="",0,T53/N53-1) -> 0.22727273 | W53: Slow mover / long tail – low price sensitivity
A54: 21 | B54: quavers small | C54: Single | E54: Active | F54: 569 | G54: 224 | H54: 34029.91 | I54: -205 | J54: -2414.8 | K54: =H54+I54+J54 -> 31410.11 | L54: =IF($K$1282=0,0,K54/$K$1282) -> 0.0026019644 | M54: =IF(F54<=0,0,K54/F54) -> 55.202302 | N54: 44.99 | O54: 1.43 | P54: =O54*'Price Groups'!$B$5 -> 32.175 | Q54: =IF(OR(N54="",P54=""),"",(N54-P54)/N54) -> 0.28484108 | R54: 2 | S54: =IF(R54="-",0,IFERROR(VLOOKUP(R54,'Price Groups'!$A$13:$C$17,3,FALSE()),0)) -> 0.18 | T54: =IF(OR(N54="",R54="-"),"",CEILING(ROUND(N54*(1+S54),2),IF(N54*(1+S54)<100,0.5,IF(N54*(1+S54)<1000,1,5)))) -> 53.5 | U54: =IF(OR(T54="",P54=""),"",(T54-P54)/T54) -> 0.39859813 | V54: =IF(T54="",0,T54/N54-1) -> 0.18915315 | W54: Core seller, medium margin (28%)
A55: 22 | B55: nescafe arabiana with Cardamom 1 pac 3 gm | C55: Single | D55: nescafe arabiana with Cardamom 20pc | E55: Active | F55: 562 | G55: 73 | H55: 47914.15 | I55: -13.16 | J55: -5013.63 | K55: =H55+I55+J55 -> 42887.36 | L55: =IF($K$1282=0,0,K55/$K$1282) -> 0.0035527219 | M55: =IF(F55<=0,0,K55/F55) -> 76.312028 | N55: 69.99 | O55: 1.6 | P55: =O55*'Price Groups'!$B$5 -> 36 | Q55: =IF(OR(N55="",P55=""),"",(N55-P55)/N55) -> 0.48564081 | R55: 2 | S55: =IF(R55="-",0,IFERROR(VLOOKUP(R55,'Price Groups'!$A$13:$C$17,3,FALSE()),0)) -> 0.18 | T55: =IF(OR(N55="",R55="-"),"",CEILING(ROUND(N55*(1+S55),2),IF(N55*(1+S55)<100,0.5,IF(N55*(1+S55)<1000,1,5)))) -> 83 | U55: =IF(OR(T55="",P55=""),"",(T55-P55)/T55) -> 0.56626506 | V55: =IF(T55="",0,T55/N55-1) -> 0.1858837 | W55: Core seller, medium margin (40%)
A56: 23 | B56: ice cream Elsaudia | C56: Single | E56: Active | F56: 556 | G56: 182 | H56: 66803.6 | I56: -768.3 | J56: 0 | K56: =H56+I56+J56 -> 66035.3 | L56: =IF($K$1282=0,0,K56/$K$1282) -> 0.0054702611 | M56: =IF(F56<=0,0,K56/F56) -> 118.76853 | N56: 129.8 | O56: 2.35 | P56: =O56*'Price Groups'!$B$5 -> 52.875 | Q56: =IF(OR(N56="",P56=""),"",(N56-P56)/N56) -> 0.59264253 | R56: 4 | S56: =IF(R56="-",0,IFERROR(VLOOKUP(R56,'Price Groups'!$A$13:$C$17,3,FALSE()),0)) -> 0.15 | T56: =IF(OR(N56="",R56="-"),"",CEILING(ROUND(N56*(1+S56),2),IF(N56*(1+S56)<100,0.5,IF(N56*(1+S56)<1000,1,5)))) -> 150 | U56: =IF(OR(T56="",P56=""),"",(T56-P56)/T56) -> 0.6475 | V56: =IF(T56="",0,T56/N56-1) -> 0.15562404 | W56: Top revenue item with healthy margin
A57: 24 | B57: Pofak Oman Cheese Flavour | C57: Single | E57: Active | F57: 552 | G57: 149 | H57: 15852.85 | I57: -135.58 | J57: -1105.9 | K57: =H57+I57+J57 -> 14611.37 | L57: =IF($K$1282=0,0,K57/$K$1282) -> 0.0012103831 | M57: =IF(F57<=0,0,K57/F57) -> 26.469873 | N57: 29.99 | O57: 0.42 | P57: =O57*'Price Groups'!$B$5 -> 9.45 | Q57: =IF(OR(N57="",P57=""),"",(N57-P57)/N57) -> 0.68489496 | R57: 3 | S57: =IF(R57="-",0,IFERROR(VLOOKUP(R57,'Price Groups'!$A$13:$C$17,3,FALSE()),0)) -> 0.16 | T57: =IF(OR(N57="",R57="-"),"",CEILING(ROUND(N57*(1+S57),2),IF(N57*(1+S57)<100,0.5,IF(N57*(1+S57)<1000,1,5)))) -> 35 | U57: =IF(OR(T57="",P57=""),"",(T57-P57)/T57) -> 0.73 | V57: =IF(T57="",0,T57/N57-1) -> 0.16705569 | W57: Core seller with healthy margin
A58: 25 | B58: Lusine | C58: Single | E58: Active | F58: 543 | G58: 127 | H58: 47964 | I58: -1891.62 | J58: -433 | K58: =H58+I58+J58 -> 45639.38 | L58: =IF($K$1282=0,0,K58/$K$1282) -> 0.0037806949 | M58: =IF(F58<=0,0,K58/F58) -> 84.050424 | Q58: =IF(OR(N58="",P58=""),"",(N58-P58)/N58) | R58: 2 | S58: =IF(R58="-",0,IFERROR(VLOOKUP(R58,'Price Groups'!$A$13:$C$17,3,FALSE()),0)) -> 0.18 | T58: =IF(OR(N58="",R58="-"),"",CEILING(ROUND(N58*(1+S58),2),IF(N58*(1+S58)<100,0.5,IF(N58*(1+S58)<1000,1,5)))) | U58: =IF(OR(T58="",P58=""),"",(T58-P58)/T58) | V58: =IFERROR(AVERAGE(V59:V66),0) -> 0.18060403 | W58: No cost in Shopify – default to core increase
B59: ↳ Lusine cheese | C59: Variant | D59: Lusine | K59: 0 | N59: 75 | Q59: =IF(OR(N59="",P59=""),"",(N59-P59)/N59) | R59: =R58 -> 2 | S59: =IF(R59="-",0,IFERROR(VLOOKUP(R59,'Price Groups'!$A$13:$C$17,3,FALSE()),0)) -> 0.18 | T59: =IF(OR(N59="",R59="-"),"",CEILING(ROUND(N59*(1+S59),2),IF(N59*(1+S59)<100,0.5,IF(N59*(1+S59)<1000,1,5)))) -> 88.5 | U59: =IF(OR(T59="",P59=""),"",(T59-P59)/T59) | V59: =IF(T59="",0,T59/N59-1) -> 0.18 | W59: Variant – same group as the product
B60: ↳ Lusine creamy cheese | C60: Variant | D60: Lusine | K60: 0 | N60: 149 | Q60: =IF(OR(N60="",P60=""),"",(N60-P60)/N60) | R60: =R58 -> 2 | S60: =IF(R60="-",0,IFERROR(VLOOKUP(R60,'Price Groups'!$A$13:$C$17,3,FALSE()),0)) -> 0.18 | T60: =IF(OR(N60="",R60="-"),"",CEILING(ROUND(N60*(1+S60),2),IF(N60*(1+S60)<100,0.5,IF(N60*(1+S60)<1000,1,5)))) -> 176 | U60: =IF(OR(T60="",P60=""),"",(T60-P60)/T60) | V60: =IF(T60="",0,T60/N60-1) -> 0.18120805 | W60: Variant – same group as the product
B61: ↳ Lusine cheese + zaatar | C61: Variant | D61: Lusine | K61: 0 | N61: 75 | Q61: =IF(OR(N61="",P61=""),"",(N61-P61)/N61) | R61: =R58 -> 2 | S61: =IF(R61="-",0,IFERROR(VLOOKUP(R61,'Price Groups'!$A$13:$C$17,3,FALSE()),0)) -> 0.18 | T61: =IF(OR(N61="",R61="-"),"",CEILING(ROUND(N61*(1+S61),2),IF(N61*(1+S61)<100,0.5,IF(N61*(1+S61)<1000,1,5)))) -> 88.5 | U61: =IF(OR(T61="",P61=""),"",(T61-P61)/T61) | V61: =IF(T61="",0,T61/N61-1) -> 0.18 | W61: Variant – same group as the product
B62: ↳ Lusine Apple | C62: Variant | D62: Lusine | K62: 0 | N62: 75 | Q62: =IF(OR(N62="",P62=""),"",(N62-P62)/N62) | R62: =R58 -> 2 | S62: =IF(R62="-",0,IFERROR(VLOOKUP(R62,'Price Groups'!$A$13:$C$17,3,FALSE()),0)) -> 0.18 | T62: =IF(OR(N62="",R62="-"),"",CEILING(ROUND(N62*(1+S62),2),IF(N62*(1+S62)<100,0.5,IF(N62*(1+S62)<1000,1,5)))) -> 88.5 | U62: =IF(OR(T62="",P62=""),"",(T62-P62)/T62) | V62: =IF(T62="",0,T62/N62-1) -> 0.18 | W62: Variant – same group as the product
B63: ↳ Lusine chocolate | C63: Variant | D63: Lusine | K63: 0 | N63: 75 | Q63: =IF(OR(N63="",P63=""),"",(N63-P63)/N63) | R63: =R58 -> 2 | S63: =IF(R63="-",0,IFERROR(VLOOKUP(R63,'Price Groups'!$A$13:$C$17,3,FALSE()),0)) -> 0.18 | T63: =IF(OR(N63="",R63="-"),"",CEILING(ROUND(N63*(1+S63),2),IF(N63*(1+S63)<100,0.5,IF(N63*(1+S63)<1000,1,5)))) -> 88.5 | U63: =IF(OR(T63="",P63=""),"",(T63-P63)/T63) | V63: =IF(T63="",0,T63/N63-1) -> 0.18 | W63: Variant – same group as the product
B64: ↳ Lusine Pizza | C64: Variant | D64: Lusine | K64: 0 | N64: 149 | Q64: =IF(OR(N64="",P64=""),"",(N64-P64)/N64) | R64: =R58 -> 2 | S64: =IF(R64="-",0,IFERROR(VLOOKUP(R64,'Price Groups'!$A$13:$C$17,3,FALSE()),0)) -> 0.18 | T64: =IF(OR(N64="",R64="-"),"",CEILING(ROUND(N64*(1+S64),2),IF(N64*(1+S64)<100,0.5,IF(N64*(1+S64)<1000,1,5)))) -> 176 | U64: =IF(OR(T64="",P64=""),"",(T64-P64)/T64) | V64: =IF(T64="",0,T64/N64-1) -> 0.18120805 | W64: Variant – same group as the product
B65: ↳ Lusine 3 cheeses | C65: Variant | D65: Lusine | K65: 0 | N65: 149 | Q65: =IF(OR(N65="",P65=""),"",(N65-P65)/N65) | R65: =R58 -> 2 | S65: =IF(R65="-",0,IFERROR(VLOOKUP(R65,'Price Groups'!$A$13:$C$17,3,FALSE()),0)) -> 0.18 | T65: =IF(OR(N65="",R65="-"),"",CEILING(ROUND(N65*(1+S65),2),IF(N65*(1+S65)<100,0.5,IF(N65*(1+S65)<1000,1,5)))) -> 176 | U65: =IF(OR(T65="",P65=""),"",(T65-P65)/T65) | V65: =IF(T65="",0,T65/N65-1) -> 0.18120805 | W65: Variant – same group as the product
B66: ↳ lusine butter croissant | C66: Variant | D66: Lusine | K66: 0 | N66: 149 | Q66: =IF(OR(N66="",P66=""),"",(N66-P66)/N66) | R66: =R58 -> 2 | S66: =IF(R66="-",0,IFERROR(VLOOKUP(R66,'Price Groups'!$A$13:$C$17,3,FALSE()),0)) -> 0.18 | T66: =IF(OR(N66="",R66="-"),"",CEILING(ROUND(N66*(1+S66),2),IF(N66*(1+S66)<100,0.5,IF(N66*(1+S66)<1000,1,5)))) -> 176 | U66: =IF(OR(T66="",P66=""),"",(T66-P66)/T66) | V66: =IF(T66="",0,T66/N66-1) -> 0.18120805 | W66: Variant – same group as the product
A67: 26 | B67: Fish Fash | C67: Single | E67: Active | F67: 536 | G67: 222 | H67: 13266.58 | I67: -160.78 | J67: -1292.44 | K67: =H67+I67+J67 -> 11813.36 | L67: =IF($K$1282=0,0,K67/$K$1282) -> 0.00097860029 | M67: =IF(F67<=0,0,K67/F67) -> 22.039851 | N67: 29.99 | O67: 0.28 | P67: =O67*'Price Groups'!$B$5 -> 6.3 | Q67: =IF(OR(N67="",P67=""),"",(N67-P67)/N67) -> 0.78992998 | R67: 5 | S67: =IF(R67="-",0,IFERROR(VLOOKUP(R67,'Price Groups'!$A$13:$C$17,3,FALSE()),0)) -> 0.02 | T67: =IF(OR(N67="",R67="-"),"",CEILING(ROUND(N67*(1+S67),2),IF(N67*(1+S67)<100,0.5,IF(N67*(1+S67)<1000,1,5)))) -> 31 | U67: =IF(OR(T67="",P67=""),"",(T67-P67)/T67) -> 0.79677419 | V67: =IF(T67="",0,T67/N67-1) -> 0.033677893 | W67: Price-sensitive best seller (frequent, cheap, high margin) – protect price image
A68: 27 | B68: tasali ketchup small | C68: Single | D68: tasali ketchup small 21 pcs | E68: Active | F68: 531 | G68: 185 | H68: 12332.66 | I68: -78.68 | J68: -249.96 | K68: =H68+I68+J68 -> 12004.02 | L68: =IF($K$1282=0,0,K68/$K$1282) -> 0.00099439426 | M68: =IF(F68<=0,0,K68/F68) -> 22.606441 | N68: 24.99 | O68: 0.42 | P68: =O68*'Price Groups'!$B$5 -> 9.45 | Q68: =IF(OR(N68="",P68=""),"",(N68-P68)/N68) -> 0.62184874 | R68: 5 | S68: =IF(R68="-",0,IFERROR(VLOOKUP(R68,'Price Groups'!$A$13:$C$17,3,FALSE()),0)) -> 0.02 | T68: =IF(OR(N68="",R68="-"),"",CEILING(ROUND(N68*(1+S68),2),IF(N68*(1+S68)<100,0.5,IF(N68*(1+S68)<1000,1,5)))) -> 25.5 | U68: =IF(OR(T68="",P68=""),"",(T68-P68)/T68) -> 0.62941176 | V68: =IF(T68="",0,T68/N68-1) -> 0.020408163 | W68: Price-sensitive best seller (frequent, cheap, high margin) – protect price image
A69: 28 | B69: lays spicy small 11 g | C69: Single | E69: Active | F69: 518 | G69: 292 | H69: 24295.7 | I69: -147.24 | J69: -3324.1 | K69: =H69+I69+J69 -> 20824.36 | L69: =IF($K$1282=0,0,K69/$K$1282) -> 0.0017250574 | M69: =IF(F69<=0,0,K69/F69) -> 40.201467 | N69: 42.9 | O69: 0.4 | P69: =O69*'Price Groups'!$B$5 -> 9 | Q69: =IF(OR(N69="",P69=""),"",(N69-P69)/N69) -> 0.79020979 | R69: 5 | S69: =IF(R69="-",0,IFERROR(VLOOKUP(R69,'Price Groups'!$A$13:$C$17,3,FALSE()),0)) -> 0.02 | T69: =IF(OR(N69="",R69="-"),"",CEILING(ROUND(N69*(1+S69),2),IF(N69*(1+S69)<100,0.5,IF(N69*(1+S69)<1000,1,5)))) -> 44 | U69: =IF(OR(T69="",P69=""),"",(T69-P69)/T69) -> 0.79545455 | V69: =IF(T69="",0,T69/N69-1) -> 0.025641026 | W69: Price-sensitive best seller (frequent, cheap, high margin) – protect price image
A70: 29 | B70: Saudi pepsi | C70: Single | E70: Active | F70: 515 | G70: 115 | H70: 32636.14 | I70: -258.51 | J70: -2857.91 | K70: =H70+I70+J70 -> 29519.72 | L70: =IF($K$1282=0,0,K70/$K$1282) -> 0.0024453675 | M70: =IF(F70<=0,0,K70/F70) -> 57.319845 | N70: 99 | O70: 2.2 | P70: =O70*'Price Groups'!$B$5 -> 49.5 | Q70: =IF(OR(N70="",P70=""),"",(N70-P70)/N70) -> 0.5 | R70: 3 | S70: =IF(R70="-",0,IFERROR(VLOOKUP(R70,'Price Groups'!$A$13:$C$17,3,FALSE()),0)) -> 0.16 | T70: =IF(OR(N70="",R70="-"),"",CEILING(ROUND(N70*(1+S70),2),IF(N70*(1+S70)<100,0.5,IF(N70*(1+S70)<1000,1,5)))) -> 115 | U70: =IF(OR(T70="",P70=""),"",(T70-P70)/T70) -> 0.56956522 | V70: =IF(T70="",0,T70/N70-1) -> 0.16161616 | W70: Core seller with healthy margin
A71: 30 | B71: Oman Chips Spicy medium pack 50 gm | C71: Single | E71: Active | F71: 500 | G71: 253 | H71: 66610.73 | I71: -3129.92 | J71: -4059.81 | K71: =H71+I71+J71 -> 59421 | L71: =IF($K$1282=0,0,K71/$K$1282) -> 0.0049223428 | M71: =IF(F71<=0,0,K71/F71) -> 118.842 | N71: 137.99 | O71: 2.8 | P71: =O71*'Price Groups'!$B$5 -> 63 | Q71: =IF(OR(N71="",P71=""),"",(N71-P71)/N71) -> 0.54344518 | R71: 4 | S71: =IF(R71="-",0,IFERROR(VLOOKUP(R71,'Price Groups'!$A$13:$C$17,3,FALSE()),0)) -> 0.15 | T71: =IF(OR(N71="",R71="-"),"",CEILING(ROUND(N71*(1+S71),2),IF(N71*(1+S71)<100,0.5,IF(N71*(1+S71)<1000,1,5)))) -> 159 | U71: =IF(OR(T71="",P71=""),"",(T71-P71)/T71) -> 0.60377358 | V71: =IF(T71="",0,T71/N71-1) -> 0.15225741 | W71: Top revenue item with healthy margin
A72: 31 | B72: Indian Crackers White | C72: Single | E72: Active | F72: 498 | G72: 233 | H72: 18631.25 | I72: -119.45 | J72: -1305.68 | K72: =H72+I72+J72 -> 17206.12 | L72: =IF($K$1282=0,0,K72/$K$1282) -> 0.0014253281 | M72: =IF(F72<=0,0,K72/F72) -> 34.550442 | N72: 44.99 | O72: 0.74 | P72: =O72*'Price Groups'!$B$5 -> 16.65 | Q72: =IF(OR(N72="",P72=""),"",(N72-P72)/N72) -> 0.62991776 | R72: 5 | S72: =IF(R72="-",0,IFERROR(VLOOKUP(R72,'Price Groups'!$A$13:$C$17,3,FALSE()),0)) -> 0.02 | T72: =IF(OR(N72="",R72="-"),"",CEILING(ROUND(N72*(1+S72),2),IF(N72*(1+S72)<100,0.5,IF(N72*(1+S72)<1000,1,5)))) -> 46 | U72: =IF(OR(T72="",P72=""),"",(T72-P72)/T72) -> 0.63804348 | V72: =IF(T72="",0,T72/N72-1) -> 0.022449433 | W72: Price-sensitive best seller (frequent, cheap, high margin) – protect price image
A73: 32 | B73: cheetos har nar Family size | C73: Single | E73: Active | F73: 489 | G73: 333 | H73: 195582.9 | I73: -2192.4 | J73: -21199.65 | K73: =H73+I73+J73 -> 172190.85 | L73: =IF($K$1282=0,0,K73/$K$1282) -> 0.014264021 | M73: =IF(F73<=0,0,K73/F73) -> 352.12853 | N73: 405.9 | O73: 7.27 | P73: =O73*'Price Groups'!$B$5 -> 163.575 | Q73: =IF(OR(N73="",P73=""),"",(N73-P73)/N73) -> 0.59700665 | R73: 4 | S73: =IF(R73="-",0,IFERROR(VLOOKUP(R73,'Price Groups'!$A$13:$C$17,3,FALSE()),0)) -> 0.15 | T73: =IF(OR(N73="",R73="-"),"",CEILING(ROUND(N73*(1+S73),2),IF(N73*(1+S73)<100,0.5,IF(N73*(1+S73)<1000,1,5)))) -> 467 | U73: =IF(OR(T73="",P73=""),"",(T73-P73)/T73) -> 0.64973233 | V73: =IF(T73="",0,T73/N73-1) -> 0.15052969 | W73: Top revenue item with healthy margin
A74: 33 | B74: lays spicy family size | C74: Single | E74: Active | F74: 469 | G74: 285 | H74: 135814.59 | I74: -2122.39 | J74: -10684.4 | K74: =H74+I74+J74 -> 123007.8 | L74: =IF($K$1282=0,0,K74/$K$1282) -> 0.010189774 | M74: =IF(F74<=0,0,K74/F74) -> 262.27676 | N74: 299.99 | O74: 6.25 | P74: =O74*'Price Groups'!$B$5 -> 140.625 | Q74: =IF(OR(N74="",P74=""),"",(N74-P74)/N74) -> 0.53123437 | R74: 4 | S74: =IF(R74="-",0,IFERROR(VLOOKUP(R74,'Price Groups'!$A$13:$C$17,3,FALSE()),0)) -> 0.15 | T74: =IF(OR(N74="",R74="-"),"",CEILING(ROUND(N74*(1+S74),2),IF(N74*(1+S74)<100,0.5,IF(N74*(1+S74)<1000,1,5)))) -> 345 | U74: =IF(OR(T74="",P74=""),"",(T74-P74)/T74) -> 0.5923913 | V74: =IF(T74="",0,T74/N74-1) -> 0.15003833 | W74: Top revenue item with healthy margin
A75: 34 | B75: Zamzam corn | C75: Single | E75: Active | F75: 468 | G75: 217 | H75: 15712.9 | I75: -68.27 | J75: -1258.24 | K75: =H75+I75+J75 -> 14386.39 | L75: =IF($K$1282=0,0,K75/$K$1282) -> 0.0011917461 | M75: =IF(F75<=0,0,K75/F75) -> 30.74015 | N75: 38.42 | O75: 0.4 | P75: =O75*'Price Groups'!$B$5 -> 9 | Q75: =IF(OR(N75="",P75=""),"",(N75-P75)/N75) -> 0.76574701 | R75: 5 | S75: =IF(R75="-",0,IFERROR(VLOOKUP(R75,'Price Groups'!$A$13:$C$17,3,FALSE()),0)) -> 0.02 | T75: =IF(OR(N75="",R75="-"),"",CEILING(ROUND(N75*(1+S75),2),IF(N75*(1+S75)<100,0.5,IF(N75*(1+S75)<1000,1,5)))) -> 39.5 | U75: =IF(OR(T75="",P75=""),"",(T75-P75)/T75) -> 0.7721519 | V75: =IF(T75="",0,T75/N75-1) -> 0.028110359 | W75: Price-sensitive best seller (frequent, cheap, high margin) – protect price image
A76: 35 | B76: Marukawa Grape Bubble Gum | C76: Single | E76: Active | F76: 467 | G76: 180 | H76: 4777 | I76: -21.95 | J76: -918.18 | K76: =H76+I76+J76 -> 3836.87 | L76: =IF($K$1282=0,0,K76/$K$1282) -> 0.00031784032 | M76: =IF(F76<=0,0,K76/F76) -> 8.2159957 | N76: 7.7 | O76: 0.24 | P76: =O76*'Price Groups'!$B$5 -> 5.4 | Q76: =IF(OR(N76="",P76=""),"",(N76-P76)/N76) -> 0.2987013 | R76: 1 | S76: =IF(R76="-",0,IFERROR(VLOOKUP(R76,'Price Groups'!$A$13:$C$17,3,FALSE()),0)) -> 0.22 | T76: =IF(OR(N76="",R76="-"),"",CEILING(ROUND(N76*(1+S76),2),IF(N76*(1+S76)<100,0.5,IF(N76*(1+S76)<1000,1,5)))) -> 9.5 | U76: =IF(OR(T76="",P76=""),"",(T76-P76)/T76) -> 0.43157895 | V76: =IF(T76="",0,T76/N76-1) -> 0.23376623 | W76: Slow mover / long tail – low price sensitivity
A77: 36 | B77: jelly pop 1 pcs | C77: Single | E77: Active | F77: 467 | G77: 79 | H77: 3980.84 | I77: -7.52 | J77: -399.95 | K77: =H77+I77+J77 -> 3573.37 | L77: =IF($K$1282=0,0,K77/$K$1282) -> 0.00029601239 | M77: =IF(F77<=0,0,K77/F77) -> 7.6517559 | N77: 11 | O77: 0.15 | P77: =O77*'Price Groups'!$B$5 -> 3.375 | Q77: =IF(OR(N77="",P77=""),"",(N77-P77)/N77) -> 0.69318182 | R77: 1 | S77: =IF(R77="-",0,IFERROR(VLOOKUP(R77,'Price Groups'!$A$13:$C$17,3,FALSE()),0)) -> 0.22 | T77: =IF(OR(N77="",R77="-"),"",CEILING(ROUND(N77*(1+S77),2),IF(N77*(1+S77)<100,0.5,IF(N77*(1+S77)<1000,1,5)))) -> 13.5 | U77: =IF(OR(T77="",P77=""),"",(T77-P77)/T77) -> 0.75 | V77: =IF(T77="",0,T77/N77-1) -> 0.22727273 | W77: Slow mover / long tail – low price sensitivity
A78: 37 | B78: kdd chocolate low fat | C78: Single | E78: Active | F78: 464 | G78: 132 | H78: 33651.75 | I78: -383.11 | J78: -7757.86 | K78: =H78+I78+J78 -> 25510.78 | L78: =IF($K$1282=0,0,K78/$K$1282) -> 0.0021132732 | M78: =IF(F78<=0,0,K78/F78) -> 54.980129 | N78: 111 | O78: 2.22 | P78: =O78*'Price Groups'!$B$5 -> 49.95 | Q78: =IF(OR(N78="",P78=""),"",(N78-P78)/N78) -> 0.55 | R78: 3 | S78: =IF(R78="-",0,IFERROR(VLOOKUP(R78,'Price Groups'!$A$13:$C$17,3,FALSE()),0)) -> 0.16 | T78: =IF(OR(N78="",R78="-"),"",CEILING(ROUND(N78*(1+S78),2),IF(N78*(1+S78)<100,0.5,IF(N78*(1+S78)<1000,1,5)))) -> 129 | U78: =IF(OR(T78="",P78=""),"",(T78-P78)/T78) -> 0.6127907 | V78: =IF(T78="",0,T78/N78-1) -> 0.16216216 | W78: Core seller with healthy margin
A79: 38 | B79: Dobbi | C79: Single | E79: Active | F79: 456 | G79: 254 | H79: 15807.1 | I79: -223.28 | J79: -1828.44 | K79: =H79+I79+J79 -> 13755.38 | L79: =IF($K$1282=0,0,K79/$K$1282) -> 0.0011394742 | M79: =IF(F79<=0,0,K79/F79) -> 30.165307 | N79: 35.03 | O79: 0.45 | P79: =O79*'Price Groups'!$B$5 -> 10.125 | Q79: =IF(OR(N79="",P79=""),"",(N79-P79)/N79) -> 0.71096203 | R79: 5 | S79: =IF(R79="-",0,IFERROR(VLOOKUP(R79,'Price Groups'!$A$13:$C$17,3,FALSE()),0)) -> 0.02 | T79: =IF(OR(N79="",R79="-"),"",CEILING(ROUND(N79*(1+S79),2),IF(N79*(1+S79)<100,0.5,IF(N79*(1+S79)<1000,1,5)))) -> 36 | U79: =IF(OR(T79="",P79=""),"",(T79-P79)/T79) -> 0.71875 | V79: =IF(T79="",0,T79/N79-1) -> 0.027690551 | W79: Price-sensitive best seller (frequent, cheap, high margin) – protect price image
A80: 39 | B80: Miska Gum 1 Pack Of 8 Pcs | C80: Single | E80: Active | F80: 456 | G80: 145 | H80: 46427.82 | I80: -49.64 | J80: -4509.35 | K80: =H80+I80+J80 -> 41868.83 | L80: =IF($K$1282=0,0,K80/$K$1282) -> 0.0034683485 | M80: =IF(F80<=0,0,K80/F80) -> 91.81761 | N80: 105.02 | O80: 2.2 | P80: =O80*'Price Groups'!$B$5 -> 49.5 | Q80: =IF(OR(N80="",P80=""),"",(N80-P80)/N80) -> 0.52866121 | R80: 4 | S80: =IF(R80="-",0,IFERROR(VLOOKUP(R80,'Price Groups'!$A$13:$C$17,3,FALSE()),0)) -> 0.15 | T80: =IF(OR(N80="",R80="-"),"",CEILING(ROUND(N80*(1+S80),2),IF(N80*(1+S80)<100,0.5,IF(N80*(1+S80)<1000,1,5)))) -> 121 | U80: =IF(OR(T80="",P80=""),"",(T80-P80)/T80) -> 0.59090909 | V80: =IF(T80="",0,T80/N80-1) -> 0.15216149 | W80: Top revenue item with healthy margin
... A84: 43 | B84: TOTTI fruiti | C84: Single | E84: Active | F84: 428 | G84: 213 | H84: 9333 | I84: -126.07 | J84: -685.58 | K84: =H84+I84+J84 -> 8521.35 | L84: =IF($K$1282=0,0,K84/$K$1282) -> 0.00070589532 | M84: =IF(F84<=0,0,K84/F84) -> 19.909696 | N84: 21 | O84: 0.47 | P84: =O84*'Price Groups'!$B$5 -> 10.575 | Q84: =IF(OR(N84="",P84=""),"",(N84-P84)/N84) -> 0.49642857 | R84: 5 | S84: =IF(R84="-",0,IFERROR(VLOOKUP(R84,'Price Groups'!$A$13:$C$17,3,FALSE()),0)) -> 0.02 | T84: =IF(OR(N84="",R84="-"),"",CEILING(ROUND(N84*(1+S84),2),IF(N84*(1+S84)<100,0.5,IF(N84*(1+S84)<1000,1,5)))) -> 21.5 | U84: =IF(OR(T84="",P84=""),"",(T84-P84)/T84) -> 0.50813953 | V84: =IF(T84="",0,T84/N84-1) -> 0.023809524 | W84: Price-sensitive best seller (frequent, cheap, high margin) – protect price image
A85: 44 | B85: ulker chocolate | C85: Single | D85: ulker chocolate 10 packs | E85: Active | F85: 416 | G85: 308 | H85: 65429.69 | I85: -378.37 | J85: -9569.76 | K85: =H85+I85+J85 -> 55481.56 | L85: =IF($K$1282=0,0,K85/$K$1282) -> 0.0045960058 | M85: =IF(F85<=0,0,K85/F85) -> 133.36913 | N85: 129.99 | O85: 3.79 | P85: =O85*'Price Groups'!$B$5 -> 85.275 | Q85: =IF(OR(N85="",P85=""),"",(N85-P85)/N85) -> 0.343988 | R85: 2 | S85: =IF(R85="-",0,IFERROR(VLOOKUP(R85,'Price Groups'!$A$13:$C$17,3,FALSE()),0)) -> 0.18 | T85: =IF(OR(N85="",R85="-"),"",CEILING(ROUND(N85*(1+S85),2),IF(N85*(1+S85)<100,0.5,IF(N85*(1+S85)<1000,1,5)))) -> 154 | U85: =IF(OR(T85="",P85=""),"",(T85-P85)/T85) -> 0.44626623 | V85: =IF(T85="",0,T85/N85-1) -> 0.18470652 | W85: Core seller, medium margin (34%)
A86: 45 | B86: crispy Salt & vinegar | C86: Single | E86: Active | F86: 409 | G86: 141 | H86: 16642.07 | I86: -77.9 | J86: -798.93 | K86: =H86+I86+J86 -> 15765.24 | L86: =IF($K$1282=0,0,K86/$K$1282) -> 0.0013059679 | M86: =IF(F86<=0,0,K86/F86) -> 38.545819 | N86: 44.99 | O86: 1.17 | P86: =O86*'Price Groups'!$B$5 -> 26.325 | Q86: =IF(OR(N86="",P86=""),"",(N86-P86)/N86) -> 0.41486997 | R86: 3 | S86: =IF(R86="-",0,IFERROR(VLOOKUP(R86,'Price Groups'!$A$13:$C$17,3,FALSE()),0)) -> 0.16 | T86: =IF(OR(N86="",R86="-"),"",CEILING(ROUND(N86*(1+S86),2),IF(N86*(1+S86)<100,0.5,IF(N86*(1+S86)<1000,1,5)))) -> 52.5 | U86: =IF(OR(T86="",P86=""),"",(T86-P86)/T86) -> 0.49857143 | V86: =IF(T86="",0,T86/N86-1) -> 0.16692598 | W86: Core seller with healthy margin
A87: 46 | B87: Elsaudia milk | C87: Single | E87: Active | F87: 404 | G87: 89 | H87: 27316.84 | I87: -5282.81 | J87: -239.24 | K87: =H87+I87+J87 -> 21794.79 | L87: =IF($K$1282=0,0,K87/$K$1282) -> 0.0018054464 | M87: =IF(F87<=0,0,K87/F87) -> 53.9475 | N87: 70 | O87: 1.45 | P87: =O87*'Price Groups'!$B$5 -> 32.625 | Q87: =IF(OR(N87="",P87=""),"",(N87-P87)/N87) -> 0.53392857 | R87: 3 | S87: =IF(R87="-",0,IFERROR(VLOOKUP(R87,'Price Groups'!$A$13:$C$17,3,FALSE()),0)) -> 0.16 | T87: =IF(OR(N87="",R87="-"),"",CEILING(ROUND(N87*(1+S87),2),IF(N87*(1+S87)<100,0.5,IF(N87*(1+S87)<1000,1,5)))) -> 81.5 | U87: =IF(OR(T87="",P87=""),"",(T87-P87)/T87) -> 0.59969325 | V87: =IF(T87="",0,T87/N87-1) -> 0.16428571 | W87: Core seller with healthy margin
A88: 47 | B88: Lay's French Cheese small | C88: Single | E88: Active | F88: 397 | G88: 221 | H88: 13891.33 | I88: -402.61 | J88: -1655.8 | K88: =H88+I88+J88 -> 11832.92 | L88: =IF($K$1282=0,0,K88/$K$1282) -> 0.00098022061 | M88: =IF(F88<=0,0,K88/F88) -> 29.805844 | N88: 29.99 | O88: 0.37 | P88: =O88*'Price Groups'!$B$5 -> 8.325 | Q88: =IF(OR(N88="",P88=""),"",(N88-P88)/N88) -> 0.72240747 | R88: 5 | S88: =IF(R88="-",0,IFERROR(VLOOKUP(R88,'Price Groups'!$A$13:$C$17,3,FALSE()),0)) -> 0.02 | T88: =IF(OR(N88="",R88="-"),"",CEILING(ROUND(N88*(1+S88),2),IF(N88*(1+S88)<100,0.5,IF(N88*(1+S88)<1000,1,5)))) -> 31 | U88: =IF(OR(T88="",P88=""),"",(T88-P88)/T88) -> 0.73145161 | V88: =IF(T88="",0,T88/N88-1) -> 0.033677893 | W88: Price-sensitive best seller (frequent, cheap, high margin) – protect price image
A89: 48 | B89: salata chipsy | C89: Single | E89: Active | F89: 387 | G89: 204 | H89: 22625.93 | I89: -224.11 | J89: -2786.1 | K89: =H89+I89+J89 -> 19615.72 | L89: =IF($K$1282=0,0,K89/$K$1282) -> 0.0016249356 | M89: =IF(F89<=0,0,K89/F89) -> 50.686615 | N89: 56.49 | O89: 0.73 | P89: =O89*'Price Groups'!$B$5 -> 16.425 | Q89: =IF(OR(N89="",P89=""),"",(N89-P89)/N89) -> 0.70924057 | R89: 3 | S89: =IF(R89="-",0,IFERROR(VLOOKUP(R89,'Price Groups'!$A$13:$C$17,3,FALSE()),0)) -> 0.16 | T89: =IF(OR(N89="",R89="-"),"",CEILING(ROUND(N89*(1+S89),2),IF(N89*(1+S89)<100,0.5,IF(N89*(1+S89)<1000,1,5)))) -> 66 | U89: =IF(OR(T89="",P89=""),"",(T89-P89)/T89) -> 0.75113636 | V89: =IF(T89="",0,T89/N89-1) -> 0.16834838 | W89: Core seller with healthy margin
A90: 49 | B90: Saudi Indomie (special chicken) | C90: Single | D90: Saudi Indomie (special chicken) 5 pc | E90: Active | F90: 382 | G90: 123 | H90: 30463.16 | I90: -5315.72 | J90: -1342.12 | K90: =H90+I90+J90 -> 23805.32 | L90: =IF($K$1282=0,0,K90/$K$1282) -> 0.0019719955 | M90: =IF(F90<=0,0,K90/F90) -> 62.317592 | N90: 83 | O90: 1.05 | P90: =O90*'Price Groups'!$B$5 -> 23.625 | Q90: =IF(OR(N90="",P90=""),"",(N90-P90)/N90) -> 0.71536145 | R90: 4 | S90: =IF(R90="-",0,IFERROR(VLOOKUP(R90,'Price Groups'!$A$13:$C$17,3,FALSE()),0)) -> 0.15 | T90: =IF(OR(N90="",R90="-"),"",CEILING(ROUND(N90*(1+S90),2),IF(N90*(1+S90)<100,0.5,IF(N90*(1+S90)<1000,1,5)))) -> 95.5 | U90: =IF(OR(T90="",P90=""),"",(T90-P90)/T90) -> 0.7526178 | V90: =IF(T90="",0,T90/N90-1) -> 0.15060241 | W90: Top revenue item with healthy margin
A91: 50 | B91: lays salt small | C91: Single | E91: Active | F91: 358 | G91: 139 | H91: 11082.94 | I91: -56.39 | J91: -1229.65 | K91: =H91+I91+J91 -> 9796.9 | L91: =IF($K$1282=0,0,K91/$K$1282) -> 0.00081155989 | M91: =IF(F91<=0,0,K91/F91) -> 27.365642 | N91: 24.99 | O91: 0.42 | P91: =O91*'Price Groups'!$B$5 -> 9.45 | Q91: =IF(OR(N91="",P91=""),"",(N91-P91)/N91) -> 0.62184874 | R91: 1 | S91: =IF(R91="-",0,IFERROR(VLOOKUP(R91,'Price Groups'!$A$13:$C$17,3,FALSE()),0)) -> 0.22 | T91: =IF(OR(N91="",R91="-"),"",CEILING(ROUND(N91*(1+S91),2),IF(N91*(1+S91)<100,0.5,IF(N91*(1+S91)<1000,1,5)))) -> 30.5 | U91: =IF(OR(T91="",P91=""),"",(T91-P91)/T91) -> 0.69016393 | V91: =IF(T91="",0,T91/N91-1) -> 0.2204882 | W91: Slow mover / long tail – low price sensitivity
A92: 51 | B92: toffo nestle | C92: Single | E92: Active | F92: 357 | G92: 158 | H92: 16755.7 | I92: -139.56 | J92: -1286.28 | K92: =H92+I92+J92 -> 15329.86 | L92: =IF($K$1282=0,0,K92/$K$1282) -> 0.0012699017 | M92: =IF(F92<=0,0,K92/F92) -> 42.940784 | N92: 49.99 | O92: 0.74 | P92: =O92*'Price Groups'!$B$5 -> 16.65 | Q92: =IF(OR(N92="",P92=""),"",(N92-P92)/N92) -> 0.66693339 | R92: 3 | S92: =IF(R92="-",0,IFERROR(VLOOKUP(R92,'Price Groups'!$A$13:$C$17,3,FALSE()),0)) -> 0.16 | T92: =IF(OR(N92="",R92="-"),"",CEILING(ROUND(N92*(1+S92),2),IF(N92*(1+S92)<100,0.5,IF(N92*(1+S92)<1000,1,5)))) -> 58 | U92: =IF(OR(T92="",P92=""),"",(T92-P92)/T92) -> 0.71293103 | V92: =IF(T92="",0,T92/N92-1) -> 0.16023205 | W92: Core seller with healthy margin
A93: 52 | B93: Pakistani noodles | C93: Single | E93: Active | F93: 356 | G93: 131 | H93: 24502.55 | I93: -261.51 | J93: -2661.66 | K93: =H93+I93+J93 -> 21579.38 | L93: =IF($K$1282=0,0,K93/$K$1282) -> 0.0017876021 | M93: =IF(F93<=0,0,K93/F93) -> 60.616236 | N93: 55 | O93: 1.08 | P93: =O93*'Price Groups'!$B$5 -> 24.3 | Q93: =IF(OR(N93="",P93=""),"",(N93-P93)/N93) -> 0.55818182 | R93: 3 | S93: =IF(R93="-",0,IFERROR(VLOOKUP(R93,'Price Groups'!$A$13:$C$17,3,FALSE()),0)) -> 0.16 | T93: =IF(OR(N93="",R93="-"),"",CEILING(ROUND(N93*(1+S93),2),IF(N93*(1+S93)<100,0.5,IF(N93*(1+S93)<1000,1,5)))) -> 64 | U93: =IF(OR(T93="",P93=""),"",(T93-P93)/T93) -> 0.6203125 | V93: =IF(T93="",0,T93/N93-1) -> 0.16363636 | W93: Core seller with healthy margin
A94: 53 | B94: kat kat Ulker chocolate | C94: Single | D94: kat kat Ulker chocolate 12 pcs | E94: Active | F94: 349 | G94: 156 | H94: 22567.71 | I94: -79.98 | J94: -6629.52 | K94: =H94+I94+J94 -> 15858.21 | L94: =IF($K$1282=0,0,K94/$K$1282) -> 0.0013136693 | M94: =IF(F94<=0,0,K94/F94) -> 45.438997 | N94: 54.99 | O94: 0.74 | P94: =O94*'Price Groups'!$B$5 -> 16.65 | Q94: =IF(OR(N94="",P94=""),"",(N94-P94)/N94) -> 0.69721768 | R94: 3 | S94: =IF(R94="-",0,IFERROR(VLOOKUP(R94,'Price Groups'!$A$13:$C$17,3,FALSE()),0)) -> 0.16 | T94: =IF(OR(N94="",R94="-"),"",CEILING(ROUND(N94*(1+S94),2),IF(N94*(1+S94)<100,0.5,IF(N94*(1+S94)<1000,1,5)))) -> 64 | U94: =IF(OR(T94="",P94=""),"",(T94-P94)/T94) -> 0.73984375 | V94: =IF(T94="",0,T94/N94-1) -> 0.16384797 | W94: Core seller with healthy margin
A95: 54 | B95: raja vegetables | C95: Single | E95: Active | F95: 334 | G95: 199 | H95: 10541.39 | I95: -104.54 | J95: -1341.05 | K95: =H95+I95+J95 -> 9095.8 | L95: =IF($K$1282=0,0,K95/$K$1282) -> 0.00075348186 | M95: =IF(F95<=0,0,K95/F95) -> 27.232934 | N95: 31.61 | O95: 0.43 | P95: =O95*'Price Groups'!$B$5 -> 9.675 | Q95: =IF(OR(N95="",P95=""),"",(N95-P95)/N95) -> 0.69392597 | R95: 5 | S95: =IF(R95="-",0,IFERROR(VLOOKUP(R95,'Price Groups'!$A$13:$C$17,3,FALSE()),0)) -> 0.02 | T95: =IF(OR(N95="",R95="-"),"",CEILING(ROUND(N95*(1+S95),2),IF(N95*(1+S95)<100,0.5,IF(N95*(1+S95)<1000,1,5)))) -> 32.5 | U95: =IF(OR(T95="",P95=""),"",(T95-P95)/T95) -> 0.70230769 | V95: =IF(T95="",0,T95/N95-1) -> 0.028155647 | W95: Price-sensitive best seller (frequent, cheap, high margin) – protect price image
A96: 55 | B96: lays ketchup small 25gm | C96: Single | E96: Active | F96: 328 | G96: 145 | H96: 12674 | I96: -153.73 | J96: -1325.26 | K96: =H96+I96+J96 -> 11195.01 | L96: =IF($K$1282=0,0,K96/$K$1282) -> 0.00092737714 | M96: =IF(F96<=0,0,K96/F96) -> 34.131128 | N96: 24.99 | O96: 0.42 | P96: =O96*'Price Groups'!$B$5 -> 9.45 | Q96: =IF(OR(N96="",P96=""),"",(N96-P96)/N96) -> 0.62184874 | R96: 3 | S96: =IF(R96="-",0,IFERROR(VLOOKUP(R96,'Price Groups'!$A$13:$C$17,3,FALSE()),0)) -> 0.16 | T96: =IF(OR(N96="",R96="-"),"",CEILING(ROUND(N96*(1+S96),2),IF(N96*(1+S96)<100,0.5,IF(N96*(1+S96)<1000,1,5)))) -> 29 | U96: =IF(OR(T96="",P96=""),"",(T96-P96)/T96) -> 0.67413793 | V96: =IF(T96="",0,T96/N96-1) -> 0.16046419 | W96: Core seller with healthy margin
A97: 56 | B97: Siip Corn Snack (roasted corn) | C97: Single | D97: Siip Corn Snack (roasted corn) 20 pcs | E97: Active | F97: 324 | G97: 79 | H97: 7647 | I97: -13.68 | J97: -452.98 | K97: =H97+I97+J97 -> 7180.34 | L97: =IF($K$1282=0,0,K97/$K$1282) -> 0.00059480815 | M97: =IF(F97<=0,0,K97/F97) -> 22.161543 | N97: 24 | O97: 0.42 | P97: =O97*'Price Groups'!$B$5 -> 9.45 | Q97: =IF(OR(N97="",P97=""),"",(N97-P97)/N97) -> 0.60625 | R97: 1 | S97: =IF(R97="-",0,IFERROR(VLOOKUP(R97,'Price Groups'!$A$13:$C$17,3,FALSE()),0)) -> 0.22 | T97: =IF(OR(N97="",R97="-"),"",CEILING(ROUND(N97*(1+S97),2),IF(N97*(1+S97)<100,0.5,IF(N97*(1+S97)<1000,1,5)))) -> 29.5 | U97: =IF(OR(T97="",P97=""),"",(T97-P97)/T97) -> 0.67966102 | V97: =IF(T97="",0,T97/N97-1) -> 0.22916667 | W97: Slow mover / long tail – low price sensitivity
A98: 57 | B98: Tarazan Chipsy | C98: Single | E98: Active | F98: 321 | G98: 170 | H98: 10446.16 | I98: -171.83 | J98: -1193.37 | K98: =H98+I98+J98 -> 9080.96 | L98: =IF($K$1282=0,0,K98/$K$1282) -> 0.00075225254 | M98: =IF(F98<=0,0,K98/F98) -> 28.289595 | N98: 35 | O98: 0.55 | P98: =O98*'Price Groups'!$B$5 -> 12.375 | Q98: =IF(OR(N98="",P98=""),"",(N98-P98)/N98) -> 0.64642857 | R98: 5 | S98: =IF(R98="-",0,IFERROR(VLOOKUP(R98,'Price Groups'!$A$13:$C$17,3,FALSE()),0)) -> 0.02 | T98: =IF(OR(N98="",R98="-"),"",CEILING(ROUND(N98*(1+S98),2),IF(N98*(1+S98)<100,0.5,IF(N98*(1+S98)<1000,1,5)))) -> 36 | U98: =IF(OR(T98="",P98=""),"",(T98-P98)/T98) -> 0.65625 | V98: =IF(T98="",0,T98/N98-1) -> 0.028571429 | W98: Price-sensitive best seller (frequent, cheap, high margin) – protect price image
A99: 58 | B99: bifa soft | C99: Single | D99: bifa soft banana 30pcs | E99: Active | F99: 315 | G99: 54 | H99: 7455.5 | I99: -40.65 | J99: -1004.09 | K99: =H99+I99+J99 -> 6410.76 | L99: =IF($K$1282=0,0,K99/$K$1282) -> 0.00053105734 | M99: =IF(F99<=0,0,K99/F99) -> 20.351619 | N99: 21 | O99: 0.42 | P99: =O99*'Price Groups'!$B$5 -> 9.45 | Q99: =IF(OR(N99="",P99=""),"",(N99-P99)/N99) -> 0.55 | R99: 1 | S99: =IF(R99="-",0,IFERROR(VLOOKUP(R99,'Price Groups'!$A$13:$C$17,3,FALSE()),0)) -> 0.22 | T99: =IF(OR(N99="",R99="-"),"",CEILING(ROUND(N99*(1+S99),2),IF(N99*(1+S99)<100,0.5,IF(N99*(1+S99)<1000,1,5)))) -> 26 | U99: =IF(OR(T99="",P99=""),"",(T99-P99)/T99) -> 0.63653846 | V99: =IF(T99="",0,T99/N99-1) -> 0.23809524 | W99: Low margin (15%)
A100: 59 | B100: fruit candy | C100: Single | E100: Active | F100: 312 | G100: 63 | H100: 3514.28 | I100: -14.06 | J100: -146 | K100: =H100+I100+J100 -> 3354.22 | L100: =IF($K$1282=0,0,K100/$K$1282) -> 0.00027785834 | M100: =IF(F100<=0,0,K100/F100) -> 10.750705 | N100: 13 | O100: 0.23 | P100: =O100*'Price Groups'!$B$5 -> 5.175 | Q100: =IF(OR(N100="",P100=""),"",(N100-P100)/N100) -> 0.60192308 | R100: 1 | S100: =IF(R100="-",0,IFERROR(VLOOKUP(R100,'Price Groups'!$A$13:$C$17,3,FALSE()),0)) -> 0.22 | T100: =IF(OR(N100="",R100="-"),"",CEILING(ROUND(N100*(1+S100),2),IF(N100*(1+S100)<100,0.5,IF(N100*(1+S100)<1000,1,5)))) -> 16 | U100: =IF(OR(T100="",P100=""),"",(T100-P100)/T100) -> 0.6765625 | V100: =IF(T100="",0,T100/N100-1) -> 0.23076923 | W100: Slow mover / long tail – low price sensitivity
A101: 60 | B101: Saudi Indomie (vegetables) | C101: Single | D101: Saudi Indomie (vegetables) 5pc | E101: Active | F101: 306 | G101: 101 | H101: 21576.1 | I101: -763.65 | J101: -1213.3 | K101: =H101+I101+J101 -> 19599.15 | L101: =IF($K$1282=0,0,K101/$K$1282) -> 0.001623563 | M101: =IF(F101<=0,0,K101/F101) -> 64.04951 | N101: 64.9 | O101: 1.15 | P101: =O101*'Price Groups'!$B$5 -> 25.875 | Q101: =IF(OR(N101="",P101=""),"",(N101-P101)/N101) -> 0.60130971 | R101: 4 | S101: =IF(R101="-",0,IFERROR(VLOOKUP(R101,'Price Groups'!$A$13:$C$17,3,FALSE()),0)) -> 0.15 | T101: =IF(OR(N101="",R101="-"),"",CEILING(ROUND(N101*(1+S101),2),IF(N101*(1+S101)<100,0.5,IF(N101*(1+S101)<1000,1,5)))) -> 75 | U101: =IF(OR(T101="",P101=""),"",(T101-P101)/T101) -> 0.655 | V101: =IF(T101="",0,T101/N101-1) -> 0.15562404 | W101: Top revenue item with healthy margin
A102: 61 | B102: salted peanuts | C102: Single | D102: salted peanuts 24pc | E102: Active | F102: 303 | G102: 128 | H102: 15956.86 | I102: -42.14 | J102: -669 | K102: =H102+I102+J102 -> 15245.72 | L102: =IF($K$1282=0,0,K102/$K$1282) -> 0.0012629316 | M102: =IF(F102<=0,0,K102/F102) -> 50.315908 | N102: 54.99 | O102: 0.39 | P102: =O102*'Price Groups'!$B$5 -> 8.775 | Q102: =IF(OR(N102="",P102=""),"",(N102-P102)/N102) -> 0.84042553 | R102: 3 | S102: =IF(R102="-",0,IFERROR(VLOOKUP(R102,'Price Groups'!$A$13:$C$17,3,FALSE()),0)) -> 0.16 | T102: =IF(OR(N102="",R102="-"),"",CEILING(ROUND(N102*(1+S102),2),IF(N102*(1+S102)<100,0.5,IF(N102*(1+S102)<1000,1,5)))) -> 64 | U102: =IF(OR(T102="",P102=""),"",(T102-P102)/T102) -> 0.86289063 | V102: =IF(T102="",0,T102/N102-1) -> 0.16384797 | W102: Core seller with healthy margin
A103: 62 | B103: siip corn snack (cheese) | C103: Single | D103: siip corn snack (cheese) 20 pcs | E103: Active | F103: 303 | G103: 51 | H103: 9205.82 | I103: -111.89 | J103: -911.06 | K103: =H103+I103+J103 -> 8182.87 | L103: =IF($K$1282=0,0,K103/$K$1282) -> 0.00067785617 | M103: =IF(F103<=0,0,K103/F103) -> 27.006172 | N103: 24.99 | O103: 0.42 | P103: =O103*'Price Groups'!$B$5 -> 9.45 | Q103: =IF(OR(N103="",P103=""),"",(N103-P103)/N103) -> 0.62184874 | R103: 3 | S103: =IF(R103="-",0,IFERROR(VLOOKUP(R103,'Price Groups'!$A$13:$C$17,3,FALSE()),0)) -> 0.16 | T103: =IF(OR(N103="",R103="-"),"",CEILING(ROUND(N103*(1+S103),2),IF(N103*(1+S103)<100,0.5,IF(N103*(1+S103)<1000,1,5)))) -> 29 | U103: =IF(OR(T103="",P103=""),"",(T103-P103)/T103) -> 0.67413793 | V103: =IF(T103="",0,T103/N103-1) -> 0.16046419 | W103: Core seller with healthy margin
A104: 63 | B104: kat kat Ulker chocolate 18g | C104: Single | D104: kat kat Ulker chocolate 30*18g | E104: Active | F104: 298 | G104: 118 | H104: 6897.13 | I104: -60.11 | J104: -1673.38 | K104: =H104+I104+J104 -> 5163.64 | L104: =IF($K$1282=0,0,K104/$K$1282) -> 0.00042774787 | M104: =IF(F104<=0,0,K104/F104) -> 17.327651 | N104: 24.99 | O104: 0.43 | P104: =O104*'Price Groups'!$B$5 -> 9.675 | Q104: =IF(OR(N104="",P104=""),"",(N104-P104)/N104) -> 0.61284514 | R104: 3 | S104: =IF(R104="-",0,IFERROR(VLOOKUP(R104,'Price Groups'!$A$13:$C$17,3,FALSE()),0)) -> 0.16 | T104: =IF(OR(N104="",R104="-"),"",CEILING(ROUND(N104*(1+S104),2),IF(N104*(1+S104)<100,0.5,IF(N104*(1+S104)<1000,1,5)))) -> 29 | U104: =IF(OR(T104="",P104=""),"",(T104-P104)/T104) -> 0.66637931 | V104: =IF(T104="",0,T104/N104-1) -> 0.16046419 | W104: Core seller with healthy margin
...

Sheet Notes
A1: How to read this file
A2: Ranking | B2: Same as the best-sellers report: units sold (1 Jan – 22 Oct 2026) descending, ties by net revenue. Products with no 2026 sales are listed at the end.
A3: Net Revenue | B3: Gross Sales + Discounts + Returns (discounts and returns are negative). Excludes shipping and tax.
A4: Unit Cost (EGP) | B4: Cost in Shopify × 15 × 1.5 (see Price Groups). AlBaik meals: 370 EGP × (14.74 / 12.5).
A5: Price Group | B5: Set per product from margin and revenue (rules on the Price Groups sheet). You can overwrite any group number 1–5 by hand.
A6: Wholesale | B6: Wholesale products (supplier tag contains جملة) always get the SAME group and % as their single item. Wholesale packs are max 15% cheaper per piece than the single (fixed in Shopify on 22 Oct 2026).
A7: New Price rounding | B7: Rounded UP: to 0.50 below 100 EGP, to 1 EGP below 1,000, to 5 EGP above.
A8: Variants | B8: Products with several variants (AlBaik, Zamzam, Altazaj, Lusine, Eid items) show sales on the product row and one row per variant (↳) with its own current and new price. All variants follow the product's group.
A9: Not repriced | B9: "special order" and the untitled custom-item line are not catalog products.
A10: Colours | B10: Blue = values from Shopify / your inputs. Black = formulas. Yellow cells on Price Groups are the levers to edit.
A11: Nothing changed in Shopify yet | B11: This file is a proposal. Prices in the store are unchanged until you approve.
