Workbook

Sheet Summary
A1: Price Changes Applied – 23/24 Oct 2026
A2: Store | B2: Tamwenat Elzekrayat (Shopify)
A3: Reason | B3: SAR→EGP 12.5 → 14.74 (+17.92%)
A4: Group increases | B4: G1 22% · G2 18% · G3 16% · G4 15% · G5 2% · Keef elmosafer = fixed prices
A6: Variants updated | B6: =COUNTA(Applied!A2:A1186) -> 1185
A7: Average change % (per item) | B7: =AVERAGE(Applied!H2:H1186) -> 0.20379785
A8: Excluded variants | B8: =COUNTA(Excluded!A2:A53) -> 52
A9: Skipped products | B9: =COUNTA(Skipped!A2:A21) -> 20
A10: Deleted products | B10: =COUNTA(Deleted!A2:A12) -> 11
A12: Rollback | B12: Old prices are in the Applied sheet and in reports/price_change_2026-10-23_rollback.json

Sheet Applied
A1: Product | B1: Variant | C1: Type | D1: Price Group | E1: Old Price (EGP) | F1: New Price (EGP) | G1: Change (EGP) | H1: Change % | I1: Reason
A2: Oman Chips spicy small pack | B2: - | C2: Single | D2: 5 | E2: 44.99 | F2: 46 | G2: =F2-E2 -> 1.01 | H2: =IF(E2=0,0,F2/E2-1) -> 0.022449433 | I2: Price-sensitive best seller (frequent, cheap, high margin) – protect price image
A3: Gandour Mastic Gum, One Piece, 2.7 Grams | B3: - | C3: Single | D3: 1 | E3: 12 | F3: 15 | G3: =F3-E3 -> 3 | H3: =IF(E3=0,0,F3/E3-1) -> 0.25 | I3: Slow mover / long tail – low price sensitivity
A4: Ghandour MESTEKA Gum 6 Pcs Pack | B4: - | C4: Single | D4: 5 | E4: 30 | F4: 31 | G4: =F4-E4 -> 1 | H4: =IF(E4=0,0,F4/E4-1) -> 0.033333333 | I4: Price-sensitive best seller (frequent, cheap, high margin) – protect price image
A5: Mirinda citrus | B5: - | C5: Single | D5: 2 | E5: 95 | F5: 113 | G5: =F5-E5 -> 18 | H5: =IF(E5=0,0,F5/E5-1) -> 0.18947368 | I5: Core seller, medium margin (40%)
A6: zamzam water 330ml | B6: - | C6: Single | D6: 4 | E6: 149.99 | F6: 173 | G6: =F6-E6 -> 23.01 | H6: =IF(E6=0,0,F6/E6-1) -> 0.15341023 | I6: Top revenue item with healthy margin
A7: Zamzam water | B7: 5 liters without cartoon | C7: Single | D7: 4 | E7: 885 | F7: 1020 | G7: =F7-E7 -> 135 | H7: =IF(E7=0,0,F7/E7-1) -> 0.15254237 | I7: Top revenue item with healthy margin
A8: Zamzam water | B8: 5 liters with cartoon | C8: Single | D8: 4 | E8: 950 | F8: 1095 | G8: =F8-E8 -> 145 | H8: =IF(E8=0,0,F8/E8-1) -> 0.15263158 | I8: Top revenue item with healthy margin
A9: Zamzam water | B9: 200 ml | C9: Single | D9: 4 | E9: 118.45 | F9: 137 | G9: =F9-E9 -> 18.55 | H9: =IF(E9=0,0,F9/E9-1) -> 0.15660616 | I9: Top revenue item with healthy margin
A10: Ulker choco sandwich | B10: - | C10: Single | D10: 3 | E10: 55.37 | F10: 64.5 | G10: =F10-E10 -> 9.13 | H10: =IF(E10=0,0,F10/E10-1) -> 0.16489074 | I10: Core seller with healthy margin
A11: Millionaire cheese corn | B11: - | C11: Single | D11: 5 | E11: 22 | F11: 22.5 | G11: =F11-E11 -> 0.5 | H11: =IF(E11=0,0,F11/E11-1) -> 0.022727273 | I11: Price-sensitive best seller (frequent, cheap, high margin) – protect price image
A12: Shani | B12: - | C12: Single | D12: 4 | E12: 99 | F12: 114 | G12: =F12-E12 -> 15 | H12: =IF(E12=0,0,F12/E12-1) -> 0.15151515 | I12: Top revenue item with healthy margin
A13: cheetos har nar | B13: - | C13: Single | D13: 5 | E13: 45 | F13: 46 | G13: =F13-E13 -> 1 | H13: =IF(E13=0,0,F13/E13-1) -> 0.022222222 | I13: Price-sensitive best seller (frequent, cheap, high margin) – protect price image
... A77: marami ketchup Flavor | B77: - | C77: Single | D77: 1 | E77: 23 | F77: 28.5 | G77: =F77-E77 -> 5.5 | H77: =IF(E77=0,0,F77/E77-1) -> 0.23913043 | I77: Slow mover / long tail – low price sensitivity
A78: keef elmosafer with cardamom 5 gm | B78: - | C78: Single | D78: Fixed | E78: 32 | F78: 29 | G78: =F78-E78 -> -3 | H78: =IF(E78=0,0,F78/E78-1) -> -0.09375 | I78: New price set by user – price drop due to high competition
A79: Heart lollipop (borgat) 1 pc. | B79: - | C79: Single | D79: 1 | E79: 14.16 | F79: 17.5 | G79: =F79-E79 -> 3.34 | H79: =IF(E79=0,0,F79/E79-1) -> 0.23587571 | I79: Slow mover / long tail – low price sensitivity
A80: Ring Candy Original | B80: - | C80: Single | D80: 1 | E80: 74.99 | F80: 91.5 | G80: =F80-E80 -> 16.51 | H80: =IF(E80=0,0,F80/E80-1) -> 0.22016269 | I80: Slow mover / long tail – low price sensitivity
A81: Saudi Indomie (red chili fried noodles) | B81: - | C81: Single | D81: 3 | E81: 82.39 | F81: 96 | G81: =F81-E81 -> 13.61 | H81: =IF(E81=0,0,F81/E81-1) -> 0.16518995 | I81: Core seller with healthy margin
A82: 7 days croissant chocolate | B82: - | C82: Single | D82: 3 | E82: 64.99 | F82: 75.5 | G82: =F82-E82 -> 10.51 | H82: =IF(E82=0,0,F82/E82-1) -> 0.16171719 | I82: Core seller with healthy margin
A83: oman chips Family Size | B83: - | C83: Single | D83: 4 | E83: 318.6 | F83: 367 | G83: =F83-E83 -> 48.4 | H83: =IF(E83=0,0,F83/E83-1) -> 0.15191463 | I83: Top revenue item with healthy margin
A84: chocolate safari | B84: - | C84: Single | D84: 3 | E84: 63.72 | F84: 74 | G84: =F84-E84 -> 10.28 | H84: =IF(E84=0,0,F84/E84-1) -> 0.16133082 | I84: Core seller with healthy margin
A85: Saudi Indomie (chicken curry) | B85: - | C85: Single | D85: 4 | E85: 63 | F85: 72.5 | G85: =F85-E85 -> 9.5 | H85: =IF(E85=0,0,F85/E85-1) -> 0.15079365 | I85: Top revenue item with healthy margin
A86: Saudi Indomie (green chili fried noodles) | B86: - | C86: Single | D86: 3 | E86: 79.73 | F86: 92.5 | G86: =F86-E86 -> 12.77 | H86: =IF(E86=0,0,F86/E86-1) -> 0.16016556 | I86: Core seller with healthy margin
A87: CRIC CRAC special flavor | B87: - | C87: Single | D87: 1 | E87: 32.77 | F87: 40 | G87: =F87-E87 -> 7.23 | H87: =IF(E87=0,0,F87/E87-1) -> 0.22062862 | I87: Slow mover / long tail – low price sensitivity
A88: Alrabee Orange Juice 125 Ml | B88: - | C88: Single | D88: 3 | E88: 49.99 | F88: 58 | G88: =F88-E88 -> 8.01 | H88: =IF(E88=0,0,F88/E88-1) -> 0.16023205 | I88: Core seller with healthy margin
A89: Elsaudia chocolate milk 200ml | B89: - | C89: Single | D89: 3 | E89: 80 | F89: 93 | G89: =F89-E89 -> 13 | H89: =IF(E89=0,0,F89/E89-1) -> 0.1625 | I89: Core seller with healthy margin
A90: indomie spicy fried noodles black | B90: - | C90: Single | D90: 3 | E90: 84.99 | F90: 99 | G90: =F90-E90 -> 14.01 | H90: =IF(E90=0,0,F90/E90-1) -> 0.16484292 | I90: Core seller with healthy margin
... A115: TOTTI Fruiti hearts | B115: - | C115: Single | D115: 1 | E115: 24.99 | F115: 30.5 | G115: =F115-E115 -> 5.51 | H115: =IF(E115=0,0,F115/E115-1) -> 0.2204882 | I115: Slow mover / long tail – low price sensitivity
A116: keef elmosafer with Saffron 30 gm | B116: - | C116: Single | D116: Fixed | E116: 135 | F116: 129 | G116: =F116-E116 -> -6 | H116: =IF(E116=0,0,F116/E116-1) -> -0.044444444 | I116: New price set by user – price drop due to high competition
A117: keef elmosafer with cardamom 30 gm | B117: - | C117: Single | D117: Fixed | E117: 139.99 | F117: 99 | G117: =F117-E117 -> -40.99 | H117: =IF(E117=0,0,F117/E117-1) -> -0.29280663 | I117: New price set by user – price drop due to high competition
A118: Fairco Hot Stix | B118: - | C118: Single | D118: 3 | E118: 149.99 | F118: 174 | G118: =F118-E118 -> 24.01 | H118: =IF(E118=0,0,F118/E118-1) -> 0.16007734 | I118: Core seller with healthy margin
A119: seno choco cream | B119: - | C119: Single | D119: 1 | E119: 16.09 | F119: 20 | G119: =F119-E119 -> 3.91 | H119: =IF(E119=0,0,F119/E119-1) -> 0.24300808 | I119: Slow mover / long tail – low price sensitivity
A120: marami BBQ flavor | B120: - | C120: Single | D120: 1 | E120: 24.99 | F120: 30.5 | G120: =F120-E120 -> 5.51 | H120: =IF(E120=0,0,F120/E120-1) -> 0.2204882 | I120: Slow mover / long tail – low price sensitivity
A121: Abu Qous (Heel Flavor) | B121: - | C121: Single | D121: 3 | E121: 140 | F121: 163 | G121: =F121-E121 -> 23 | H121: =IF(E121=0,0,F121/E121-1) -> 0.16428571 | I121: Core seller with healthy margin
A122: indian red crackers large pack | B122: - | C122: Single | D122: 3 | E122: 189.99 | F122: 221 | G122: =F122-E122 -> 31.01 | H122: =IF(E122=0,0,F122/E122-1) -> 0.16321912 | I122: Core seller with healthy margin
A123: Ice cream toy | B123: - | C123: Single | D123: 1 | E123: 35 | F123: 43 | G123: =F123-E123 -> 8 | H123: =IF(E123=0,0,F123/E123-1) -> 0.22857143 | I123: Slow mover / long tail – low price sensitivity
A124: borgat gummy raspderry & blackberry | B124: - | C124: Single | D124: 1 | E124: 23.62 | F124: 29 | G124: =F124-E124 -> 5.38 | H124: =IF(E124=0,0,F124/E124-1) -> 0.22777307 | I124: Slow mover / long tail – low price sensitivity
A125: Crispy ABC Family Ketchup | B125: - | C125: Single | D125: 3 | E125: 190 | F125: 221 | G125: =F125-E125 -> 31 | H125: =IF(E125=0,0,F125/E125-1) -> 0.16315789 | I125: Core seller with healthy margin
A126: Fairco Salted Sticks | B126: - | C126: Single | D126: 3 | E126: 190 | F126: 221 | G126: =F126-E126 -> 31 | H126: =IF(E126=0,0,F126/E126-1) -> 0.16315789 | I126: Core seller with healthy margin
A127: Pofak Oman family Cheese Flavour | B127: - | C127: Single | D127: 2 | E127: 94.99 | F127: 113 | G127: =F127-E127 -> 18.01 | H127: =IF(E127=0,0,F127/E127-1) -> 0.18959891 | I127: Core seller, medium margin (33%)
A128: Rabea Karak Tea With Cardamom 1 pc | B128: - | C128: Single | D128: 4 | E128: 109.99 | F128: 127 | G128: =F128-E128 -> 17.01 | H128: =IF(E128=0,0,F128/E128-1) -> 0.15465042 | I128: Top revenue item with healthy margin
A129: triangular wafer | B129: - | C129: Single | D129: 1 | E129: 30.74 | F129: 37.5 | G129: =F129-E129 -> 6.76 | H129: =IF(E129=0,0,F129/E129-1) -> 0.21990891 | I129: Slow mover / long tail – low price sensitivity
... A166: Elyamama Cake Vanilla | B166: - | C166: Single | D166: 1 | E166: 29.99 | F166: 37 | G166: =F166-E166 -> 7.01 | H166: =IF(E166=0,0,F166/E166-1) -> 0.23374458 | I166: Slow mover / long tail – low price sensitivity
A167: keef elmosafer with Saffron 5 gm | B167: - | C167: Single | D167: Fixed | E167: 32 | F167: 35 | G167: =F167-E167 -> 3 | H167: =IF(E167=0,0,F167/E167-1) -> 0.09375 | I167: New price set by user
A168: Batook Banana Gum | B168: - | C168: Single | D168: 1 | E168: 14.99 | F168: 18.5 | G168: =F168-E168 -> 3.51 | H168: =IF(E168=0,0,F168/E168-1) -> 0.2341561 | I168: Slow mover / long tail – low price sensitivity
A169: Borgat Gummy ringlets | B169: - | C169: Single | D169: 1 | E169: 15.38 | F169: 19 | G169: =F169-E169 -> 3.62 | H169: =IF(E169=0,0,F169/E169-1) -> 0.23537061 | I169: Slow mover / long tail – low price sensitivity
A170: alin hot chanachur | B170: - | C170: Single | D170: 1 | E170: 34.99 | F170: 43 | G170: =F170-E170 -> 8.01 | H170: =IF(E170=0,0,F170/E170-1) -> 0.22892255 | I170: Slow mover / long tail – low price sensitivity
A171: indofood sweet soy sauce | B171: - | C171: Single | D171: 3 | E171: 249.99 | F171: 290 | G171: =F171-E171 -> 40.01 | H171: =IF(E171=0,0,F171/E171-1) -> 0.1600464 | I171: Core seller with healthy margin
A172: chocolate rico wafer | B172: - | C172: Single | D172: 1 | E172: 24.99 | F172: 30.5 | G172: =F172-E172 -> 5.51 | H172: =IF(E172=0,0,F172/E172-1) -> 0.2204882 | I172: Slow mover / long tail – low price sensitivity
A173: rana hot sauce 474ml | B173: - | C173: Single | D173: 3 | E173: 129.99 | F173: 151 | G173: =F173-E173 -> 21.01 | H173: =IF(E173=0,0,F173/E173-1) -> 0.16162782 | I173: Core seller with healthy margin
A174: Memories tea biscuit 150g | B174: - | C174: Single | D174: 1 | E174: 49.99 | F174: 61 | G174: =F174-E174 -> 11.01 | H174: =IF(E174=0,0,F174/E174-1) -> 0.22024405 | I174: Slow mover / long tail – low price sensitivity
A175: Original Iranian Saffron 1gm | B175: - | C175: Single | D175: 3 | E175: 346.5 | F175: 402 | G175: =F175-E175 -> 55.5 | H175: =IF(E175=0,0,F175/E175-1) -> 0.16017316 | I175: Core seller with healthy margin
A176: Twizzlers Strawberry low fat 70g | B176: - | C176: Single | D176: 1 | E176: 80 | F176: 98 | G176: =F176-E176 -> 18 | H176: =IF(E176=0,0,F176/E176-1) -> 0.225 | I176: Low margin (3%)
A177: Abo walad chocolate wafer | B177: - | C177: Single | D177: 1 | E177: 17.28 | F177: 21.5 | G177: =F177-E177 -> 4.22 | H177: =IF(E177=0,0,F177/E177-1) -> 0.24421296 | I177: Slow mover / long tail – low price sensitivity
A178: Saudi Indomie (special chicken) 5 pc | B178: - | C178: Wholesale | D178: 4 | E178: 380 | F178: 437 | G178: =F178-E178 -> 57 | H178: =IF(E178=0,0,F178/E178-1) -> 0.15 | I178: Wholesale – same group as its single "Saudi Indomie (special chicken)"
A179: TOTTI Fruiti cola | B179: - | C179: Single | D179: 1 | E179: 24.99 | F179: 30.5 | G179: =F179-E179 -> 5.51 | H179: =IF(E179=0,0,F179/E179-1) -> 0.2204882 | I179: Slow mover / long tail – low price sensitivity
... A971: gum stick fruit flavor 1pcs | B971: - | C971: Single | D971: 1 | E971: 11 | F971: 13.5 | G971: =F971-E971 -> 2.5 | H971: =IF(E971=0,0,F971/E971-1) -> 0.22727273 | I971: Slow mover / long tail – low price sensitivity
A972: keef elmosafer Saudi Coffee with cardamom , 12 pieces *(5g) | B972: - | C972: Wholesale | D972: Fixed | E972: 349.99 | F972: 359 | G972: =F972-E972 -> 9.01 | H972: =IF(E972=0,0,F972/E972-1) -> 0.025743593 | I972: New price set by user
A973: kettle cooked balsamico & tomato 150g | B973: - | C973: Single | D973: 1 | E973: 219.99 | F973: 269 | G973: =F973-E973 -> 49.01 | H973: =IF(E973=0,0,F973/E973-1) -> 0.22278285 | I973: Slow mover / long tail – low price sensitivity
A974: kwality ice cream toffee | B974: - | C974: Single | D974: 1 | E974: 149.99 | F974: 183 | G974: =F974-E974 -> 33.01 | H974: =IF(E974=0,0,F974/E974-1) -> 0.22008134 | I974: Slow mover / long tail – low price sensitivity
A975: lays stax sour cream & onion 100g | B975: - | C975: Single | D975: 1 | E975: 249.99 | F975: 305 | G975: =F975-E975 -> 55.01 | H975: =IF(E975=0,0,F975/E975-1) -> 0.2200488 | I975: Slow mover / long tail – low price sensitivity
A976: mega chips kebab 50g | B976: - | C976: Single | D976: 1 | E976: 74.99 | F976: 91.5 | G976: =F976-E976 -> 16.51 | H976: =IF(E976=0,0,F976/E976-1) -> 0.22016269 | I976: Slow mover / long tail – low price sensitivity
A977: mentos gum breeze mint 12pcs | B977: - | C977: Single | D977: 1 | E977: 110 | F977: 135 | G977: =F977-E977 -> 25 | H977: =IF(E977=0,0,F977/E977-1) -> 0.22727273 | I977: Slow mover / long tail – low price sensitivity
A978: milka chocolate happy cows | B978: - | C978: Single | D978: 1 | E978: 85.41 | F978: 105 | G978: =F978-E978 -> 19.59 | H978: =IF(E978=0,0,F978/E978-1) -> 0.22936424 | I978: Low margin (13%)
A979: milka chocolate raisins & nuts | B979: - | C979: Single | D979: 1 | E979: 85.41 | F979: 105 | G979: =F979-E979 -> 19.59 | H979: =IF(E979=0,0,F979/E979-1) -> 0.22936424 | I979: Low margin (13%)
A980: millet dates cake 350g | B980: - | C980: Single | D980: 1 | E980: 349.99 | F980: 427 | G980: =F980-E980 -> 77.01 | H980: =IF(E980=0,0,F980/E980-1) -> 0.22003486 | I980: Slow mover / long tail – low price sensitivity
A981: my boba mango 170g | B981: - | C981: Single | D981: 1 | E981: 99.99 | F981: 122 | G981: =F981-E981 -> 22.01 | H981: =IF(E981=0,0,F981/E981-1) -> 0.22012201 | I981: Slow mover / long tail – low price sensitivity
A982: punjabi Alshalaan amber rice 5kg | B982: - | C982: Single | D982: 5 | E982: 1100 | F982: 1125 | G982: =F982-E982 -> 25 | H982: =IF(E982=0,0,F982/E982-1) -> 0.022727273 | I982: Lowest increase – set by user (staple coffee / rice / tea)
A983: reese,s nut bar peanut butter 47g | B983: - | C983: Single | D983: 1 | E983: 95 | F983: 116 | G983: =F983-E983 -> 21 | H983: =IF(E983=0,0,F983/E983-1) -> 0.22105263 | I983: Slow mover / long tail – low price sensitivity
A984: sanabel alshahed dates maamoul 400g | B984: - | C984: Single | D984: 1 | E984: 499.99 | F984: 610 | G984: =F984-E984 -> 110.01 | H984: =IF(E984=0,0,F984/E984-1) -> 0.2200244 | I984: Slow mover / long tail – low price sensitivity
... A1065: just kettle chips salt & vinegar 125g | B1065: - | C1065: Single | D1065: 1 | E1065: 159.99 | F1065: 196 | G1065: =F1065-E1065 -> 36.01 | H1065: =IF(E1065=0,0,F1065/E1065-1) -> 0.22507657 | I1065: Slow mover / long tail – low price sensitivity
A1066: keef elmosafer Saudi Coffee with cardamom, 10 pieces * (30g) | B1066: - | C1066: Wholesale | D1066: Fixed | E1066: 1250 | F1066: 969 | G1066: =F1066-E1066 -> -281 | H1066: =IF(E1066=0,0,F1066/E1066-1) -> -0.2248 | I1066: New price set by user – price drop due to high competition
A1067: kikna cinnamon dates cake 15pieces | B1067: - | C1067: Single | D1067: 1 | E1067: 349.99 | F1067: 427 | G1067: =F1067-E1067 -> 77.01 | H1067: =IF(E1067=0,0,F1067/E1067-1) -> 0.22003486 | I1067: Slow mover / long tail – low price sensitivity
A1068: krupuk siliana 400g | B1068: - | C1068: Single | D1068: 1 | E1068: 499.99 | F1068: 610 | G1068: =F1068-E1068 -> 110.01 | H1068: =IF(E1068=0,0,F1068/E1068-1) -> 0.2200244 | I1068: Slow mover / long tail – low price sensitivity
A1069: lays stax bqq 100g | B1069: - | C1069: Single | D1069: 1 | E1069: 259.99 | F1069: 318 | G1069: =F1069-E1069 -> 58.01 | H1069: =IF(E1069=0,0,F1069/E1069-1) -> 0.22312397 | I1069: Slow mover / long tail – low price sensitivity
A1070: milka chocolate broken hazelnut | B1070: - | C1070: Single | D1070: 1 | E1070: 85.41 | F1070: 105 | G1070: =F1070-E1070 -> 19.59 | H1070: =IF(E1070=0,0,F1070/E1070-1) -> 0.22936424 | I1070: Low margin (13%)
A1071: milka chocolate chips cookies | B1071: - | C1071: Single | D1071: 1 | E1071: 85.41 | F1071: 105 | G1071: =F1071-E1071 -> 19.59 | H1071: =IF(E1071=0,0,F1071/E1071-1) -> 0.22936424 | I1071: Low margin (13%)
A1072: milka chocolate strawberry cilekli | B1072: - | C1072: Single | D1072: 1 | E1072: 105.74 | F1072: 129 | G1072: =F1072-E1072 -> 23.26 | H1072: =IF(E1072=0,0,F1072/E1072-1) -> 0.21997352 | I1072: Slow mover / long tail – low price sensitivity
A1073: milka joghurt yoghurt 100g | B1073: - | C1073: Single | D1073: 1 | E1073: 149.99 | F1073: 183 | G1073: =F1073-E1073 -> 33.01 | H1073: =IF(E1073=0,0,F1073/E1073-1) -> 0.22008134 | I1073: Slow mover / long tail – low price sensitivity
A1074: my boba cola 170g | B1074: - | C1074: Single | D1074: 1 | E1074: 99.99 | F1074: 122 | G1074: =F1074-E1074 -> 22.01 | H1074: =IF(E1074=0,0,F1074/E1074-1) -> 0.22012201 | I1074: Slow mover / long tail – low price sensitivity
A1075: natural organic sea salt 500g | B1075: - | C1075: Single | D1075: 1 | E1075: 179.99 | F1075: 220 | G1075: =F1075-E1075 -> 40.01 | H1075: =IF(E1075=0,0,F1075/E1075-1) -> 0.22229013 | I1075: Slow mover / long tail – low price sensitivity
A1076: rebel assaf 150 ml | B1076: - | C1076: Single | D1076: 1 | E1076: 2500 | F1076: 3050 | G1076: =F1076-E1076 -> 550 | H1076: =IF(E1076=0,0,F1076/E1076-1) -> 0.22 | I1076: Slow mover / long tail – low price sensitivity
A1077: skittles wild berry 20g | B1077: - | C1077: Single | D1077: 1 | E1077: 151.99 | F1077: 186 | G1077: =F1077-E1077 -> 34.01 | H1077: =IF(E1077=0,0,F1077/E1077-1) -> 0.22376472 | I1077: Slow mover / long tail – low price sensitivity
A1078: sun sip Can Popping Boba Tea With peach 325ml | B1078: - | C1078: Single | D1078: 1 | E1078: 84.99 | F1078: 104 | G1078: =F1078-E1078 -> 19.01 | H1078: =IF(E1078=0,0,F1078/E1078-1) -> 0.22367337 | I1078: Slow mover / long tail – low price sensitivity
... A1114: just kettle chips salt & black pepper 125g | B1114: - | C1114: Single | D1114: 1 | E1114: 159.99 | F1114: 196 | G1114: =F1114-E1114 -> 36.01 | H1114: =IF(E1114=0,0,F1114/E1114-1) -> 0.22507657 | I1114: Slow mover / long tail – low price sensitivity
A1115: keef elmosafer Saudi Coffee with Saffron, 12 pieces (5g) | B1115: - | C1115: Wholesale | D1115: Fixed | E1115: 349.99 | F1115: 368 | G1115: =F1115-E1115 -> 18.01 | H1115: =IF(E1115=0,0,F1115/E1115-1) -> 0.051458613 | I1115: New price set by user
A1116: kettle cooked sea salt 150g | B1116: - | C1116: Single | D1116: 1 | E1116: 219.99 | F1116: 269 | G1116: =F1116-E1116 -> 49.01 | H1116: =IF(E1116=0,0,F1116/E1116-1) -> 0.22278285 | I1116: Slow mover / long tail – low price sensitivity
A1117: luban Musk ibraq | B1117: - | C1117: Single | D1117: 2 | E1117: 2500 | F1117: 2950 | G1117: =F1117-E1117 -> 450 | H1117: =IF(E1117=0,0,F1117/E1117-1) -> 0.18 | I1117: No cost in Shopify – default to core increase
A1118: mega chips lemon & chili 50g | B1118: - | C1118: Single | D1118: 1 | E1118: 74.99 | F1118: 91.5 | G1118: =F1118-E1118 -> 16.51 | H1118: =IF(E1118=0,0,F1118/E1118-1) -> 0.22016269 | I1118: Slow mover / long tail – low price sensitivity
A1119: milka chocolate riso soffiato | B1119: - | C1119: Single | D1119: 1 | E1119: 85.41 | F1119: 105 | G1119: =F1119-E1119 -> 19.59 | H1119: =IF(E1119=0,0,F1119/E1119-1) -> 0.22936424 | I1119: Low margin (13%)
A1120: nescafe arabiana with saffron 1 pac 30g 1 pack of 10 pcs | B1120: - | C1120: Wholesale | D1120: 3 | E1120: 2600 | F1120: 3020 | G1120: =F1120-E1120 -> 420 | H1120: =IF(E1120=0,0,F1120/E1120-1) -> 0.16153846 | I1120: Wholesale – same group as its single "nescafe arabiana with safaran 1 pac 30g"
A1121: protein bar one reese,s 18g protein | B1121: - | C1121: Single | D1121: 1 | E1121: 350 | F1121: 427 | G1121: =F1121-E1121 -> 77 | H1121: =IF(E1121=0,0,F1121/E1121-1) -> 0.22 | I1121: Slow mover / long tail – low price sensitivity
A1122: rio mare tuna salad kukurydza 160g | B1122: - | C1122: Single | D1122: 1 | E1122: 599.99 | F1122: 732 | G1122: =F1122-E1122 -> 132.01 | H1122: =IF(E1122=0,0,F1122/E1122-1) -> 0.22002033 | I1122: Slow mover / long tail – low price sensitivity
A1123: rio mare tuna salad kuskus 160g | B1123: - | C1123: Single | D1123: 1 | E1123: 599.99 | F1123: 732 | G1123: =F1123-E1123 -> 132.01 | H1123: =IF(E1123=0,0,F1123/E1123-1) -> 0.22002033 | I1123: Slow mover / long tail – low price sensitivity
A1124: rio mare tuna salad meksykan 160g | B1124: - | C1124: Single | D1124: 1 | E1124: 599.99 | F1124: 732 | G1124: =F1124-E1124 -> 132.01 | H1124: =IF(E1124=0,0,F1124/E1124-1) -> 0.22002033 | I1124: Slow mover / long tail – low price sensitivity
A1125: top fruit mango jelly candy 800g | B1125: - | C1125: Single | D1125: 1 | E1125: 649.99 | F1125: 793 | G1125: =F1125-E1125 -> 143.01 | H1125: =IF(E1125=0,0,F1125/E1125-1) -> 0.22001877 | I1125: Slow mover / long tail – low price sensitivity
A1126: turkish black coffee 250g | B1126: - | C1126: Single | D1126: 1 | E1126: 649.99 | F1126: 793 | G1126: =F1126-E1126 -> 143.01 | H1126: =IF(E1126=0,0,F1126/E1126-1) -> 0.22001877 | I1126: Slow mover / long tail – low price sensitivity
A1127: white chocolate dragee | B1127: - | C1127: Single | D1127: 1 | E1127: 89.09 | F1127: 109 | G1127: =F1127-E1127 -> 19.91 | H1127: =IF(E1127=0,0,F1127/E1127-1) -> 0.22348187 | I1127: Slow mover / long tail – low price sensitivity
... A1156: Hello Panda Biscuits large pack 234g | B1156: - | C1156: Single | D1156: 1 | E1156: 249.99 | F1156: 305 | G1156: =F1156-E1156 -> 55.01 | H1156: =IF(E1156=0,0,F1156/E1156-1) -> 0.2200488 | I1156: Slow mover / long tail – low price sensitivity
A1157: keef elmosafer Saudi Coffee with Saffron, 10 pieces (30g) | B1157: - | C1157: Wholesale | D1157: Fixed | E1157: 1200 | F1157: 1170 | G1157: =F1157-E1157 -> -30 | H1157: =IF(E1157=0,0,F1157/E1157-1) -> -0.025 | I1157: New price set by user – price drop due to high competition
...

Sheet Excluded
A1: Product | B1: Variant | C1: Price (EGP, 22 Oct) | D1: Note
A2: AlBaik meals | B2: Spicy 4 pcs broasted chicken | C2: 580 | D2: Excluded by owner – price not changed
A3: AlBaik meals | B3: Regular 4 pcs broasted chicken | C3: 580 | D3: Excluded by owner – price not changed
A4: AlBaik meals | B4: Spicy 10 pcs mesahhab | C4: 580 | D4: Excluded by owner – price not changed
A5: AlBaik meals | B5: Regular 10 pcs mesahhab | C5: 580 | D5: Excluded by owner – price not changed
A6: AlBaik meals | B6: Big Baik regular | C6: 420 | D6: Excluded by owner – price not changed
A7: AlBaik meals | B7: Big Baik regular + cheese | C7: 480 | D7: Excluded by owner – price not changed
A8: AlBaik meals | B8: Big Baik spicy | C8: 420 | D8: Excluded by owner – price not changed
A9: AlBaik meals | B9: Big Baik Spicy +cheese | C9: 480 | D9: Excluded by owner – price not changed
A10: AlBaik meals | B10: extra cocktail sauce | C10: 65 | D10: Excluded by owner – price not changed
A11: AlBaik meals | B11: extra garlic sauce | C11: 65 | D11: Excluded by owner – price not changed
A12: AlBaik meals | B12: extra Mesahhab sauce | C12: 65 | D12: Excluded by owner – price not changed
A13: AlBaik meals | B13: Shawarma sandwich with garlic sauce spaicy | C13: 240 | D13: Excluded by owner – price not changed
... A53: Almarai mix berry juice | B53: - | C53: 410 | D53: Excluded by owner – price not changed

Sheet Skipped
A1: Product | B1: Price Group | C1: Price in Analysis | D1: Live Price (23 Oct) | E1: Planned New Price | F1: Reason
A2: tasali spicy small | B2: 3 | C2: 29.99 | D2: 24.99 | E2: 35 | F2: Price changed in Shopify after the 22-Oct analysis – review manually
A3: nescafe arabiana with safaran 1 pac 3 gm | B3: 1 | C3: 49.99 | D3: 30 | E3: 61 | F3: Price changed in Shopify after the 22-Oct analysis – review manually
A4: lays spicy mediam size 60g | B4: 2 | C4: 119.99 | D4: 60 | E4: 142 | F4: Price changed in Shopify after the 22-Oct analysis – review manually
A5: time candy | B5: 1 | C5: 8.22 | D5: 14 | E5: 10.5 | F5: Price changed in Shopify after the 22-Oct analysis – review manually
A6: Cake bar 7 days chocolate | B6: 1 | C6: 34.99 | D6: 29.99 | E6: 43 | F6: Price changed in Shopify after the 22-Oct analysis – review manually
A7: Chocolate Paste | B7: 1 | C7: 6.22 | D7: 16.15 | E7: 8 | F7: Price changed in Shopify after the 22-Oct analysis – review manually
A8: Saudi Indomie (baladi chicken) | B8: 3 | C8: 55 | D8: 75 | E8: 64 | F8: Price changed in Shopify after the 22-Oct analysis – review manually
A9: Marie Biscuits | B9: 1 | C9: 36 | D9: 49.99 | E9: 44 | F9: Price changed in Shopify after the 22-Oct analysis – review manually
A10: Saudi Indomie (baladi chicken) 5 pc | B10: 3 | C10: 250 | D10: 325 | E10: 290 | F10: Price changed in Shopify after the 22-Oct analysis – review manually
A11: abu kass rice 5kg | B11: 5 | C11: 850 | D11: 910 | E11: 867 | F11: Price changed in Shopify after the 22-Oct analysis – review manually
A12: Borgat Gummy bumble bear | B12: 1 | C12: 9.92 | D12: 19.95 | E12: 12.5 | F12: Price changed in Shopify after the 22-Oct analysis – review manually
A13: Miaw Miaw BBQ | B13: 1 | C13: 120 | D13: 100 | E13: 147 | F13: Price changed in Shopify after the 22-Oct analysis – review manually
... A18: golden potato spicy 65g | B18: 1 | C18: 149.99 | D18: 119.99 | E18: 183 | F18: Price changed in Shopify after the 22-Oct analysis – review manually
A19: millionaire corn curls | B19: 1 | C19: 11.05 | E19: 13.5 | F19: Product renamed in Shopify – not found
A20: Fine Rabea Leaf Tea 400 | B20: 3 | C20: 650 | E20: 754 | F20: Product renamed in Shopify – not found
A21: toffo deemah salted caramel | B21: 1 | C21: 350 | E21: 427 | F21: Product renamed in Shopify – not found

Sheet Deleted
A1: Product | B1: Price Group | C1: Last Price | D1: Planned New Price | E1: Status
A2: alameed turkish coffee without cardamom 250g | B2: 1 | C2: 575 | D2: 702 | E2: Was DRAFT/suspended – deleted from Shopify on 24 Oct (owner request)
A3: Al Ameed turkish Light Coffee without cardamom 250g | B3: 1 | C3: 574.99 | D3: 702 | E3: Was DRAFT/suspended – deleted from Shopify on 24 Oct (owner request)
A4: Al Ameed turkish black Coffee 250g | B4: 1 | C4: 574.99 | D4: 702 | E4: Was DRAFT/suspended – deleted from Shopify on 24 Oct (owner request)
A5: Al Ameed turkish black Coffee without cardamom 250g | B5: 1 | C5: 574.99 | D5: 702 | E5: Was DRAFT/suspended – deleted from Shopify on 24 Oct (owner request)
A6: alameed coffee french 250g | B6: 1 | C6: 574.99 | D6: 702 | E6: Was DRAFT/suspended – deleted from Shopify on 24 Oct (owner request)
A7: alameed coffee french hazelnut 250g | B7: 1 | C7: 599.99 | D7: 732 | E7: Was DRAFT/suspended – deleted from Shopify on 24 Oct (owner request)
A8: Al Ameed turkish Light Coffee 250g | B8: 1 | C8: 574.99 | D8: 702 | E8: Was DRAFT/suspended – deleted from Shopify on 24 Oct (owner request)
A9: alameed turkish coffee 250g | B9: 1 | C9: 575 | D9: 702 | E9: Was DRAFT/suspended – deleted from Shopify on 24 Oct (owner request)
A10: Al Ameed Decaf without cardamom Coffee 250g | B10: 1 | C10: 649.99 | D10: 793 | E10: Was DRAFT/suspended – deleted from Shopify on 24 Oct (owner request)
A11: alameed coffee french mistka 250g | B11: 1 | C11: 600 | D11: 732 | E11: Was DRAFT/suspended – deleted from Shopify on 24 Oct (owner request)
A12: alameed coffee french orangina 250g | B12: 1 | C12: 599.99 | D12: 732 | E12: Was DRAFT/suspended – deleted from Shopify on 24 Oct (owner request)
